Computer_Architecture/HDL1(Sequential)/Counter/7bit Up Counter/Adder.v
module adder (
    input wire [6:0] I,
    output wire [6:0] O
);

assign O = I + 1;    
endmodule

HDL1(Sequential)/Counter/7bit Up Counter/register.v
module register (
    input wire clk,
    input wire reset,
    input wire [6:0] d,
    output reg [6:0] q
);

always @(posedge clk,posedge reset) begin
    if(reset) q<=7'b0000000;
    else q<=d;
end    
endmodule

Computer_Architecture/HDL1(Sequential)/Counter/7bit Up Counter/counter.v
module counter (
    input wire clk,
    input wire reset,
    output wire [6:0] q
);

wire [6:0] q_temp,d_temp;
register circ1(clk,reset,d_temp,q_temp);
adder circ2(q_temp,d_temp);

assign q = q_temp;
    
endmodule

HDL1(Sequential)/Counter/7bit Up Counter/counter_tb.v
`timescale 1ns/1ns

module counter_tb;

reg clk;
reg reset;
wire [6:0] q;

counter circ(clk,reset,q);

always begin
    clk = ~clk;
    #10;
end

initial begin
    $dumpfile("test.vcd");
    $dumpvars(0,counter_tb);

    clk<=0;
    reset<=1;
    #20;
    reset<=0;
    #20;
    #20;
    #20;
    #20;
    #20;
    #20;
    $finish;
end

initial begin
    $monitor("clk=%b,reset=%b,q=%b",clk,reset,q);
end
endmodule

Computer_Architecture/HDL1(Sequential)/Counter/7bit Up Counter/test.vcd
$date
	Mon May 13 09:01:21 2024
$end
$version
	Icarus Verilog
$end
$timescale
	1ns
$end
$scope module counter_tb $end
$var wire 7 ! q [6:0] $end
$var reg 1 " clk $end
$var reg 1 # reset $end
$scope module circ $end
$var wire 1 " clk $end
$var wire 7 $ q [6:0] $end
$var wire 1 # reset $end
$var wire 7 % q_temp [6:0] $end
$var wire 7 & d_temp [6:0] $end
$scope module circ1 $end
$var wire 1 " clk $end
$var wire 1 # reset $end
$var wire 7 ' d [6:0] $end
$var reg 7 ( q [6:0] $end
$upscope $end
$scope module circ2 $end
$var wire 7 ) I [6:0] $end
$var wire 7 * O [6:0] $end
$upscope $end
$upscope $end
$upscope $end
$enddefinitions $end
$comment Show the parameter values. $end
$dumpall
$end
#0
$dumpvars
b1 *
b0 )
b0 (
b1 '
b1 &
b0 %
b0 $
1#
0"
b0 !
$end
#10
1"
#20
0#
0"
#30
b10 &
b10 '
b10 *
b1 !
b1 $
b1 %
b1 (
b1 )
1"
#40
0"
#50
b11 &
b11 '
b11 *
b10 !
b10 $
b10 %
b10 (
b10 )
1"
#60
0"
#70
b100 &
b100 '
b100 *
b11 !
b11 $
b11 %
b11 (
b11 )
1"
#80
0"
#90
b101 &
b101 '
b101 *
b100 !
b100 $
b100 %
b100 (
b100 )
1"
#100
0"
#110
b110 &
b110 '
b110 *
b101 !
b101 $
b101 %
b101 (
b101 )
1"
#120
0"
#130
b111 &
b111 '
b111 *
b110 !
b110 $
b110 %
b110 (
b110 )
1"
#140
0"
#150
b1000 &
b1000 '
b1000 *
b111 !
b111 $
b111 %
b111 (
b111 )
1"
#160
0"
#170
b1001 &
b1001 '
b1001 *
b1000 !
b1000 $
b1000 %
b1000 (
b1000 )
1"
#180
0"
#190
b1010 &
b1010 '
b1010 *
b1001 !
b1001 $
b1001 %
b1001 (
b1001 )
1"
#200
0"
#210
b1011 &
b1011 '
b1011 *
b1010 !
b1010 $
b1010 %
b1010 (
b1010 )
1"
#220
0"
#230
b1100 &
b1100 '
b1100 *
b1011 !
b1011 $
b1011 %
b1011 (
b1011 )
1"
#240
0"
#250
b1101 &
b1101 '
b1101 *
b1100 !
b1100 $
b1100 %
b1100 (
b1100 )
1"
#260
0"
#270
b1110 &
b1110 '
b1110 *
b1101 !
b1101 $
b1101 %
b1101 (
b1101 )
1"
#280
0"
#290
b1111 &
b1111 '
b1111 *
b1110 !
b1110 $
b1110 %
b1110 (
b1110 )
1"
#300
0"
#310
b10000 &
b10000 '
b10000 *
b1111 !
b1111 $
b1111 %
b1111 (
b1111 )
1"
#320
0"
#330
b10001 &
b10001 '
b10001 *
b10000 !
b10000 $
b10000 %
b10000 (
b10000 )
1"
#340
0"
#350
b10010 &
b10010 '
b10010 *
b10001 !
b10001 $
b10001 %
b10001 (
b10001 )
1"
#360
0"
#370
b10011 &
b10011 '
b10011 *
b10010 !
b10010 $
b10010 %
b10010 (
b10010 )
1"
#380
0"
#390
b10100 &
b10100 '
b10100 *
b10011 !
b10011 $
b10011 %
b10011 (
b10011 )
1"
#400
0"
#410
b10101 &
b10101 '
b10101 *
b10100 !
b10100 $
b10100 %
b10100 (
b10100 )
1"
#420
0"
#430
b10110 &
b10110 '
b10110 *
b10101 !
b10101 $
b10101 %
b10101 (
b10101 )
1"
#440
0"
#450
b10111 &
b10111 '
b10111 *
b10110 !
b10110 $
b10110 %
b10110 (
b10110 )
1"
#460
0"
#470
b11000 &
b11000 '
b11000 *
b10111 !
b10111 $
b10111 %
b10111 (
b10111 )
1"
#480
0"
#490
b11001 &
b11001 '
b11001 *
b11000 !
b11000 $
b11000 %
b11000 (
b11000 )
1"
#500
0"
#510
b11010 &
b11010 '
b11010 *
b11001 !
b11001 $
b11001 %
b11001 (
b11001 )
1"
#520
0"
#530
b11011 &
b11011 '
b11011 *
b11010 !
b11010 $
b11010 %
b11010 (
b11010 )
1"
#540
0"
#550
b11100 &
b11100 '
b11100 *
b11011 !
b11011 $
b11011 %
b11011 (
b11011 )
1"
#560
0"
#570
b11101 &
b11101 '
b11101 *
b11100 !
b11100 $
b11100 %
b11100 (
b11100 )
1"
#580
0"
#590
b11110 &
b11110 '
b11110 *
b11101 !
b11101 $
b11101 %
b11101 (
b11101 )
1"
#600
0"
#610
b11111 &
b11111 '
b11111 *
b11110 !
b11110 $
b11110 %
b11110 (
b11110 )
1"
#620
0"
#630
b100000 &
b100000 '
b100000 *
b11111 !
b11111 $
b11111 %
b11111 (
b11111 )
1"
#640
0"
#650
b100001 &
b100001 '
b100001 *
b100000 !
b100000 $
b100000 %
b100000 (
b100000 )
1"
#660
0"
#670
b100010 &
b100010 '
b100010 *
b100001 !
b100001 $
b100001 %
b100001 (
b100001 )
1"
#680
0"
#690
b100011 &
b100011 '
b100011 *
b100010 !
b100010 $
b100010 %
b100010 (
b100010 )
1"
#700
0"
#710
b100100 &
b100100 '
b100100 *
b100011 !
b100011 $
b100011 %
b100011 (
b100011 )
1"
#720
0"
#730
b100101 &
b100101 '
b100101 *
b100100 !
b100100 $
b100100 %
b100100 (
b100100 )
1"
#740
0"
#750
b100110 &
b100110 '
b100110 *
b100101 !
b100101 $
b100101 %
b100101 (
b100101 )
1"
#760
0"
#770
b100111 &
b100111 '
b100111 *
b100110 !
b100110 $
b100110 %
b100110 (
b100110 )
1"
#780
0"
#790
b101000 &
b101000 '
b101000 *
b100111 !
b100111 $
b100111 %
b100111 (
b100111 )
1"
#800
0"
#810
b101001 &
b101001 '
b101001 *
b101000 !
b101000 $
b101000 %
b101000 (
b101000 )
1"
#820
0"
#830
b101010 &
b101010 '
b101010 *
b101001 !
b101001 $
b101001 %
b101001 (
b101001 )
1"
#840
0"
#850
b101011 &
b101011 '
b101011 *
b101010 !
b101010 $
b101010 %
b101010 (
b101010 )
1"
#860
0"
#870
b101100 &
b101100 '
b101100 *
b101011 !
b101011 $
b101011 %
b101011 (
b101011 )
1"
#880
0"
#890
b101101 &
b101101 '
b101101 *
b101100 !
b101100 $
b101100 %
b101100 (
b101100 )
1"
#900
0"
#910
b101110 &
b101110 '
b101110 *
b101101 !
b101101 $
b101101 %
b101101 (
b101101 )
1"
#920
0"
#930
b101111 &
b101111 '
b101111 *
b101110 !
b101110 $
b101110 %
b101110 (
b101110 )
1"
#940
0"
#950
b110000 &
b110000 '
b110000 *
b101111 !
b101111 $
b101111 %
b101111 (
b101111 )
1"
#960
0"
#970
b110001 &
b110001 '
b110001 *
b110000 !
b110000 $
b110000 %
b110000 (
b110000 )
1"
#980
0"
#990
b110010 &
b110010 '
b110010 *
b110001 !
b110001 $
b110001 %
b110001 (
b110001 )
1"
#1000
0"
#1010
b110011 &
b110011 '
b110011 *
b110010 !
b110010 $
b110010 %
b110010 (
b110010 )
1"
#1020
0"
#1030
b110100 &
b110100 '
b110100 *
b110011 !
b110011 $
b110011 %
b110011 (
b110011 )
1"
#1040
0"
#1050
b110101 &
b110101 '
b110101 *
b110100 !
b110100 $
b110100 %
b110100 (
b110100 )
1"
#1060
0"
#1070
b110110 &
b110110 '
b110110 *
b110101 !
b110101 $
b110101 %
b110101 (
b110101 )
1"
#1080
0"
#1090
b110111 &
b110111 '
b110111 *
b110110 !
b110110 $
b110110 %
b110110 (
b110110 )
1"
#1100
0"
#1110
b111000 &
b111000 '
b111000 *
b110111 !
b110111 $
b110111 %
b110111 (
b110111 )
1"
#1120
0"
#1130
b111001 &
b111001 '
b111001 *
b111000 !
b111000 $
b111000 %
b111000 (
b111000 )
1"
#1140
0"
#1150
b111010 &
b111010 '
b111010 *
b111001 !
b111001 $
b111001 %
b111001 (
b111001 )
1"
#1160
0"
#1170
b111011 &
b111011 '
b111011 *
b111010 !
b111010 $
b111010 %
b111010 (
b111010 )
1"
#1180
0"
#1190
b111100 &
b111100 '
b111100 *
b111011 !
b111011 $
b111011 %
b111011 (
b111011 )
1"
#1200
0"
#1210
b111101 &
b111101 '
b111101 *
b111100 !
b111100 $
b111100 %
b111100 (
b111100 )
1"
#1220
0"
#1230
b111110 &
b111110 '
b111110 *
b111101 !
b111101 $
b111101 %
b111101 (
b111101 )
1"
#1240
0"
#1250
b111111 &
b111111 '
b111111 *
b111110 !
b111110 $
b111110 %
b111110 (
b111110 )
1"
#1260
0"
#1270
b1000000 &
b1000000 '
b1000000 *
b111111 !
b111111 $
b111111 %
b111111 (
b111111 )
1"
#1280
0"
#1290
b1000001 &
b1000001 '
b1000001 *
b1000000 !
b1000000 $
b1000000 %
b1000000 (
b1000000 )
1"
#1300
0"
#1310
b1000010 &
b1000010 '
b1000010 *
b1000001 !
b1000001 $
b1000001 %
b1000001 (
b1000001 )
1"
#1320
0"
#1330
b1000011 &
b1000011 '
b1000011 *
b1000010 !
b1000010 $
b1000010 %
b1000010 (
b1000010 )
1"
#1340
0"
#1350
b1000100 &
b1000100 '
b1000100 *
b1000011 !
b1000011 $
b1000011 %
b1000011 (
b1000011 )
1"
#1360
0"
#1370
b1000101 &
b1000101 '
b1000101 *
b1000100 !
b1000100 $
b1000100 %
b1000100 (
b1000100 )
1"
#1380
0"
#1390
b1000110 &
b1000110 '
b1000110 *
b1000101 !
b1000101 $
b1000101 %
b1000101 (
b1000101 )
1"
#1400
0"
#1410
b1000111 &
b1000111 '
b1000111 *
b1000110 !
b1000110 $
b1000110 %
b1000110 (
b1000110 )
1"
#1420
0"
#1430
b1001000 &
b1001000 '
b1001000 *
b1000111 !
b1000111 $
b1000111 %
b1000111 (
b1000111 )
1"
#1440
0"
#1450
b1001001 &
b1001001 '
b1001001 *
b1001000 !
b1001000 $
b1001000 %
b1001000 (
b1001000 )
1"
#1460
0"
#1470
b1001010 &
b1001010 '
b1001010 *
b1001001 !
b1001001 $
b1001001 %
b1001001 (
b1001001 )
1"
#1480
0"
#1490
b1001011 &
b1001011 '
b1001011 *
b1001010 !
b1001010 $
b1001010 %
b1001010 (
b1001010 )
1"
#1500
0"
#1510
b1001100 &
b1001100 '
b1001100 *
b1001011 !
b1001011 $
b1001011 %
b1001011 (
b1001011 )
1"
#1520
0"
#1530
b1001101 &
b1001101 '
b1001101 *
b1001100 !
b1001100 $
b1001100 %
b1001100 (
b1001100 )
1"
#1540
0"
#1550
b1001110 &
b1001110 '
b1001110 *
b1001101 !
b1001101 $
b1001101 %
b1001101 (
b1001101 )
1"
#1560
0"
#1570
b1001111 &
b1001111 '
b1001111 *
b1001110 !
b1001110 $
b1001110 %
b1001110 (
b1001110 )
1"
#1580
0"
#1590
b1010000 &
b1010000 '
b1010000 *
b1001111 !
b1001111 $
b1001111 %
b1001111 (
b1001111 )
1"
#1600
0"
#1610
b1010001 &
b1010001 '
b1010001 *
b1010000 !
b1010000 $
b1010000 %
b1010000 (
b1010000 )
1"
#1620
0"
#1630
b1010010 &
b1010010 '
b1010010 *
b1010001 !
b1010001 $
b1010001 %
b1010001 (
b1010001 )
1"
#1640
0"
#1650
b1010011 &
b1010011 '
b1010011 *
b1010010 !
b1010010 $
b1010010 %
b1010010 (
b1010010 )
1"
#1660
0"
#1670
b1010100 &
b1010100 '
b1010100 *
b1010011 !
b1010011 $
b1010011 %
b1010011 (
b1010011 )
1"
#1680
0"
#1690
b1010101 &
b1010101 '
b1010101 *
b1010100 !
b1010100 $
b1010100 %
b1010100 (
b1010100 )
1"
#1700
0"
#1710
b1010110 &
b1010110 '
b1010110 *
b1010101 !
b1010101 $
b1010101 %
b1010101 (
b1010101 )
1"
#1720
0"
#1730
b1010111 &
b1010111 '
b1010111 *
b1010110 !
b1010110 $
b1010110 %
b1010110 (
b1010110 )
1"
#1740
0"
#1750
b1011000 &
b1011000 '
b1011000 *
b1010111 !
b1010111 $
b1010111 %
b1010111 (
b1010111 )
1"
#1760
0"
#1770
b1011001 &
b1011001 '
b1011001 *
b1011000 !
b1011000 $
b1011000 %
b1011000 (
b1011000 )
1"
#1780
0"
#1790
b1011010 &
b1011010 '
b1011010 *
b1011001 !
b1011001 $
b1011001 %
b1011001 (
b1011001 )
1"
#1800
0"
#1810
b1011011 &
b1011011 '
b1011011 *
b1011010 !
b1011010 $
b1011010 %
b1011010 (
b1011010 )
1"
#1820
0"
#1830
b1011100 &
b1011100 '
b1011100 *
b1011011 !
b1011011 $
b1011011 %
b1011011 (
b1011011 )
1"
#1840
0"
#1850
b1011101 &
b1011101 '
b1011101 *
b1011100 !
b1011100 $
b1011100 %
b1011100 (
b1011100 )
1"
#1860
0"
#1870
b1011110 &
b1011110 '
b1011110 *
b1011101 !
b1011101 $
b1011101 %
b1011101 (
b1011101 )
1"
#1880
0"
#1890
b1011111 &
b1011111 '
b1011111 *
b1011110 !
b1011110 $
b1011110 %
b1011110 (
b1011110 )
1"
#1900
0"
#1910
b1100000 &
b1100000 '
b1100000 *
b1011111 !
b1011111 $
b1011111 %
b1011111 (
b1011111 )
1"
#1920
0"
#1930
b1100001 &
b1100001 '
b1100001 *
b1100000 !
b1100000 $
b1100000 %
b1100000 (
b1100000 )
1"
#1940
0"
#1950
b1100010 &
b1100010 '
b1100010 *
b1100001 !
b1100001 $
b1100001 %
b1100001 (
b1100001 )
1"
#1960
0"
#1970
b1100011 &
b1100011 '
b1100011 *
b1100010 !
b1100010 $
b1100010 %
b1100010 (
b1100010 )
1"
#1980
0"
#1990
b1100100 &
b1100100 '
b1100100 *
b1100011 !
b1100011 $
b1100011 %
b1100011 (
b1100011 )
1"
#2000
0"
#2010
b1100101 &
b1100101 '
b1100101 *
b1100100 !
b1100100 $
b1100100 %
b1100100 (
b1100100 )
1"
#2020
0"
#2030
b1100110 &
b1100110 '
b1100110 *
b1100101 !
b1100101 $
b1100101 %
b1100101 (
b1100101 )
1"
#2040
0"
#2050
b1100111 &
b1100111 '
b1100111 *
b1100110 !
b1100110 $
b1100110 %
b1100110 (
b1100110 )
1"
#2060
0"
#2070
b1101000 &
b1101000 '
b1101000 *
b1100111 !
b1100111 $
b1100111 %
b1100111 (
b1100111 )
1"
#2080
0"
#2090
b1101001 &
b1101001 '
b1101001 *
b1101000 !
b1101000 $
b1101000 %
b1101000 (
b1101000 )
1"
#2100
0"
#2110
b1101010 &
b1101010 '
b1101010 *
b1101001 !
b1101001 $
b1101001 %
b1101001 (
b1101001 )
1"
#2120
0"
#2130
b1101011 &
b1101011 '
b1101011 *
b1101010 !
b1101010 $
b1101010 %
b1101010 (
b1101010 )
1"
#2140
0"
#2150
b1101100 &
b1101100 '
b1101100 *
b1101011 !
b1101011 $
b1101011 %
b1101011 (
b1101011 )
1"
#2160
0"
#2170
b1101101 &
b1101101 '
b1101101 *
b1101100 !
b1101100 $
b1101100 %
b1101100 (
b1101100 )
1"
#2180
0"
#2190
b1101110 &
b1101110 '
b1101110 *
b1101101 !
b1101101 $
b1101101 %
b1101101 (
b1101101 )
1"
#2200
0"
#2210
b1101111 &
b1101111 '
b1101111 *
b1101110 !
b1101110 $
b1101110 %
b1101110 (
b1101110 )
1"
#2220
0"
#2230
b1110000 &
b1110000 '
b1110000 *
b1101111 !
b1101111 $
b1101111 %
b1101111 (
b1101111 )
1"
#2240
0"
#2250
b1110001 &
b1110001 '
b1110001 *
b1110000 !
b1110000 $
b1110000 %
b1110000 (
b1110000 )
1"
#2260
0"
#2270
b1110010 &
b1110010 '
b1110010 *
b1110001 !
b1110001 $
b1110001 %
b1110001 (
b1110001 )
1"
#2280
0"
#2290
b1110011 &
b1110011 '
b1110011 *
b1110010 !
b1110010 $
b1110010 %
b1110010 (
b1110010 )
1"
#2300
0"
#2310
b1110100 &
b1110100 '
b1110100 *
b1110011 !
b1110011 $
b1110011 %
b1110011 (
b1110011 )
1"
#2320
0"
#2330
b1110101 &
b1110101 '
b1110101 *
b1110100 !
b1110100 $
b1110100 %
b1110100 (
b1110100 )
1"
#2340
0"
#2350
b1110110 &
b1110110 '
b1110110 *
b1110101 !
b1110101 $
b1110101 %
b1110101 (
b1110101 )
1"
#2360
0"
#2370
b1110111 &
b1110111 '
b1110111 *
b1110110 !
b1110110 $
b1110110 %
b1110110 (
b1110110 )
1"
#2380
0"
#2390
b1111000 &
b1111000 '
b1111000 *
b1110111 !
b1110111 $
b1110111 %
b1110111 (
b1110111 )
1"
#2400
0"
#2410
b1111001 &
b1111001 '
b1111001 *
b1111000 !
b1111000 $
b1111000 %
b1111000 (
b1111000 )
1"
#2420
0"
#2430
b1111010 &
b1111010 '
b1111010 *
b1111001 !
b1111001 $
b1111001 %
b1111001 (
b1111001 )
1"
#2440
0"
#2450
b1111011 &
b1111011 '
b1111011 *
b1111010 !
b1111010 $
b1111010 %
b1111010 (
b1111010 )
1"
#2460
0"
#2470
b1111100 &
b1111100 '
b1111100 *
b1111011 !
b1111011 $
b1111011 %
b1111011 (
b1111011 )
1"
#2480
0"
#2490
b1111101 &
b1111101 '
b1111101 *
b1111100 !
b1111100 $
b1111100 %
b1111100 (
b1111100 )
1"
#2500
0"
#2510
b1111110 &
b1111110 '
b1111110 *
b1111101 !
b1111101 $
b1111101 %
b1111101 (
b1111101 )
1"
#2520
0"
#2530
b1111111 &
b1111111 '
b1111111 *
b1111110 !
b1111110 $
b1111110 %
b1111110 (
b1111110 )
1"
#2540
0"
#2550
b0 &
b0 '
b0 *
b1111111 !
b1111111 $
b1111111 %
b1111111 (
b1111111 )
1"
#2560
0"
#2570
b1 &
b1 '
b1 *
b0 !
b0 $
b0 %
b0 (
b0 )
1"
#2580
0"
#2590
b10 &
b10 '
b10 *
b1 !
b1 $
b1 %
b1 (
b1 )
1"
#2600
0"
#2610
b11 &
b11 '
b11 *
b10 !
b10 $
b10 %
b10 (
b10 )
1"
#2620
0"
#2630
b100 &
b100 '
b100 *
b11 !
b11 $
b11 %
b11 (
b11 )
1"
#2640
0"
#2650
b101 &
b101 '
b101 *
b100 !
b100 $
b100 %
b100 (
b100 )
1"
#2660
0"
#2670
b110 &
b110 '
b110 *
b101 !
b101 $
b101 %
b101 (
b101 )
1"
#2680
0"
#2690
b111 &
b111 '
b111 *
b110 !
b110 $
b110 %
b110 (
b110 )
1"
#2700
0"
#2710
b1000 &
b1000 '
b1000 *
b111 !
b111 $
b111 %
b111 (
b111 )
1"
#2720
0"
#2730
b1001 &
b1001 '
b1001 *
b1000 !
b1000 $
b1000 %
b1000 (
b1000 )
1"
#2740
0"
#2750
b1010 &
b1010 '
b1010 *
b1001 !
b1001 $
b1001 %
b1001 (
b1001 )
1"
#2760
0"
#2770
b1011 &
b1011 '
b1011 *
b1010 !
b1010 $
b1010 %
b1010 (
b1010 )
1"
#2780
0"
#2790
b1100 &
b1100 '
b1100 *
b1011 !
b1011 $
b1011 %
b1011 (
b1011 )
1"
#2800
0"
#2810
b1101 &
b1101 '
b1101 *
b1100 !
b1100 $
b1100 %
b1100 (
b1100 )
1"
#2820
0"
#2830
b1110 &
b1110 '
b1110 *
b1101 !
b1101 $
b1101 %
b1101 (
b1101 )
1"
#2840
0"
#2850
b1111 &
b1111 '
b1111 *
b1110 !
b1110 $
b1110 %
b1110 (
b1110 )
1"
#2860
0"
#2870
b10000 &
b10000 '
b10000 *
b1111 !
b1111 $
b1111 %
b1111 (
b1111 )
1"
#2880
0"
#2890
b10001 &
b10001 '
b10001 *
b10000 !
b10000 $
b10000 %
b10000 (
b10000 )
1"
#2900
0"
#2910
b10010 &
b10010 '
b10010 *
b10001 !
b10001 $
b10001 %
b10001 (
b10001 )
1"
#2920
0"
#2930
b10011 &
b10011 '
b10011 *
b10010 !
b10010 $
b10010 %
b10010 (
b10010 )
1"
#2940
0"
#2950
b10100 &
b10100 '
b10100 *
b10011 !
b10011 $
b10011 %
b10011 (
b10011 )
1"
#2960
0"
#2970
b10101 &
b10101 '
b10101 *
b10100 !
b10100 $
b10100 %
b10100 (
b10100 )
1"
#2980
0"
#2990
b10110 &
b10110 '
b10110 *
b10101 !
b10101 $
b10101 %
b10101 (
b10101 )
1"
#3000
0"
#3010
b10111 &
b10111 '
b10111 *
b10110 !
b10110 $
b10110 %
b10110 (
b10110 )
1"
#3020
0"
#3030
b11000 &
b11000 '
b11000 *
b10111 !
b10111 $
b10111 %
b10111 (
b10111 )
1"
#3040
0"
#3050
b11001 &
b11001 '
b11001 *
b11000 !
b11000 $
b11000 %
b11000 (
b11000 )
1"
#3060
0"
#3070
b11010 &
b11010 '
b11010 *
b11001 !
b11001 $
b11001 %
b11001 (
b11001 )
1"
#3080
0"
#3090
b11011 &
b11011 '
b11011 *
b11010 !
b11010 $
b11010 %
b11010 (
b11010 )
1"
#3100
0"
#3110
b11100 &
b11100 '
b11100 *
b11011 !
b11011 $
b11011 %
b11011 (
b11011 )
1"
#3120
0"
#3130
b11101 &
b11101 '
b11101 *
b11100 !
b11100 $
b11100 %
b11100 (
b11100 )
1"
#3140
0"
#3150
b11110 &
b11110 '
b11110 *
b11101 !
b11101 $
b11101 %
b11101 (
b11101 )
1"
#3160
0"
#3170
b11111 &
b11111 '
b11111 *
b11110 !
b11110 $
b11110 %
b11110 (
b11110 )
1"
#3180
0"
#3190
b100000 &
b100000 '
b100000 *
b11111 !
b11111 $
b11111 %
b11111 (
b11111 )
1"
#3200
0"
#3210
b100001 &
b100001 '
b100001 *
b100000 !
b100000 $
b100000 %
b100000 (
b100000 )
1"
#3220
0"
#3230
b100010 &
b100010 '
b100010 *
b100001 !
b100001 $
b100001 %
b100001 (
b100001 )
1"
#3240
0"
#3250
b100011 &
b100011 '
b100011 *
b100010 !
b100010 $
b100010 %
b100010 (
b100010 )
1"
#3260
0"
#3270
b100100 &
b100100 '
b100100 *
b100011 !
b100011 $
b100011 %
b100011 (
b100011 )
1"
#3280
0"
#3290
b100101 &
b100101 '
b100101 *
b100100 !
b100100 $
b100100 %
b100100 (
b100100 )
1"
#3300
0"
#3310
b100110 &
b100110 '
b100110 *
b100101 !
b100101 $
b100101 %
b100101 (
b100101 )
1"
#3320
0"
#3330
b100111 &
b100111 '
b100111 *
b100110 !
b100110 $
b100110 %
b100110 (
b100110 )
1"
#3340
0"
#3350
b101000 &
b101000 '
b101000 *
b100111 !
b100111 $
b100111 %
b100111 (
b100111 )
1"
#3360
0"
#3370
b101001 &
b101001 '
b101001 *
b101000 !
b101000 $
b101000 %
b101000 (
b101000 )
1"
#3380
0"
#3390
b101010 &
b101010 '
b101010 *
b101001 !
b101001 $
b101001 %
b101001 (
b101001 )
1"
#3400
0"
#3410
b101011 &
b101011 '
b101011 *
b101010 !
b101010 $
b101010 %
b101010 (
b101010 )
1"
#3420
0"
#3430
b101100 &
b101100 '
b101100 *
b101011 !
b101011 $
b101011 %
b101011 (
b101011 )
1"
#3440
0"
#3450
b101101 &
b101101 '
b101101 *
b101100 !
b101100 $
b101100 %
b101100 (
b101100 )
1"
#3460
0"
#3470
b101110 &
b101110 '
b101110 *
b101101 !
b101101 $
b101101 %
b101101 (
b101101 )
1"
#3480
0"
#3490
b101111 &
b101111 '
b101111 *
b101110 !
b101110 $
b101110 %
b101110 (
b101110 )
1"
#3500
0"
#3510
b110000 &
b110000 '
b110000 *
b101111 !
b101111 $
b101111 %
b101111 (
b101111 )
1"
#3520
0"
#3530
b110001 &
b110001 '
b110001 *
b110000 !
b110000 $
b110000 %
b110000 (
b110000 )
1"
#3540
0"
#3550
b110010 &
b110010 '
b110010 *
b110001 !
b110001 $
b110001 %
b110001 (
b110001 )
1"
#3560
0"
#3570
b110011 &
b110011 '
b110011 *
b110010 !
b110010 $
b110010 %
b110010 (
b110010 )
1"
#3580
0"
#3590
b110100 &
b110100 '
b110100 *
b110011 !
b110011 $
b110011 %
b110011 (
b110011 )
1"
#3600
0"
#3610
b110101 &
b110101 '
b110101 *
b110100 !
b110100 $
b110100 %
b110100 (
b110100 )
1"
#3620
0"
#3630
b110110 &
b110110 '
b110110 *
b110101 !
b110101 $
b110101 %
b110101 (
b110101 )
1"
#3640
0"
#3650
b110111 &
b110111 '
b110111 *
b110110 !
b110110 $
b110110 %
b110110 (
b110110 )
1"
#3660
0"
#3670
b111000 &
b111000 '
b111000 *
b110111 !
b110111 $
b110111 %
b110111 (
b110111 )
1"
#3680
0"
#3690
b111001 &
b111001 '
b111001 *
b111000 !
b111000 $
b111000 %
b111000 (
b111000 )
1"
#3700
0"
#3710
b111010 &
b111010 '
b111010 *
b111001 !
b111001 $
b111001 %
b111001 (
b111001 )
1"
#3720
0"
#3730
b111011 &
b111011 '
b111011 *
b111010 !
b111010 $
b111010 %
b111010 (
b111010 )
1"
#3740
0"
#3750
b111100 &
b111100 '
b111100 *
b111011 !
b111011 $
b111011 %
b111011 (
b111011 )
1"
#3760
0"
#3770
b111101 &
b111101 '
b111101 *
b111100 !
b111100 $
b111100 %
b111100 (
b111100 )
1"
#3780
0"
#3790
b111110 &
b111110 '
b111110 *
b111101 !
b111101 $
b111101 %
b111101 (
b111101 )
1"
#3800
0"
#3810
b111111 &
b111111 '
b111111 *
b111110 !
b111110 $
b111110 %
b111110 (
b111110 )
1"
#3820
0"
#3830
b1000000 &
b1000000 '
b1000000 *
b111111 !
b111111 $
b111111 %
b111111 (
b111111 )
1"
#3840
0"
#3850
b1000001 &
b1000001 '
b1000001 *
b1000000 !
b1000000 $
b1000000 %
b1000000 (
b1000000 )
1"
#3860
0"
#3870
b1000010 &
b1000010 '
b1000010 *
b1000001 !
b1000001 $
b1000001 %
b1000001 (
b1000001 )
1"
#3880
0"
#3890
b1000011 &
b1000011 '
b1000011 *
b1000010 !
b1000010 $
b1000010 %
b1000010 (
b1000010 )
1"
#3900
0"
#3910
b1000100 &
b1000100 '
b1000100 *
b1000011 !
b1000011 $
b1000011 %
b1000011 (
b1000011 )
1"
#3920
0"
#3930
b1000101 &
b1000101 '
b1000101 *
b1000100 !
b1000100 $
b1000100 %
b1000100 (
b1000100 )
1"
#3940
0"
#3950
b1000110 &
b1000110 '
b1000110 *
b1000101 !
b1000101 $
b1000101 %
b1000101 (
b1000101 )
1"
#3960
0"
#3970
b1000111 &
b1000111 '
b1000111 *
b1000110 !
b1000110 $
b1000110 %
b1000110 (
b1000110 )
1"
#3980
0"
#3990
b1001000 &
b1001000 '
b1001000 *
b1000111 !
b1000111 $
b1000111 %
b1000111 (
b1000111 )
1"
#4000
0"
#4010
b1001001 &
b1001001 '
b1001001 *
b1001000 !
b1001000 $
b1001000 %
b1001000 (
b1001000 )
1"
#4020
0"
#4030
b1001010 &
b1001010 '
b1001010 *
b1001001 !
b1001001 $
b1001001 %
b1001001 (
b1001001 )
1"
#4040
0"
#4050
b1001011 &
b1001011 '
b1001011 *
b1001010 !
b1001010 $
b1001010 %
b1001010 (
b1001010 )
1"
#4060
0"
#4070
b1001100 &
b1001100 '
b1001100 *
b1001011 !
b1001011 $
b1001011 %
b1001011 (
b1001011 )
1"
#4080
0"
#4090
b1001101 &
b1001101 '
b1001101 *
b1001100 !
b1001100 $
b1001100 %
b1001100 (
b1001100 )
1"
#4100
0"
#4110
b1001110 &
b1001110 '
b1001110 *
b1001101 !
b1001101 $
b1001101 %
b1001101 (
b1001101 )
1"
#4120
0"
#4130
b1001111 &
b1001111 '
b1001111 *
b1001110 !
b1001110 $
b1001110 %
b1001110 (
b1001110 )
1"
#4140
0"
#4150
b1010000 &
b1010000 '
b1010000 *
b1001111 !
b1001111 $
b1001111 %
b1001111 (
b1001111 )
1"
#4160
0"
#4170
b1010001 &
b1010001 '
b1010001 *
b1010000 !
b1010000 $
b1010000 %
b1010000 (
b1010000 )
1"
#4180
0"
#4190
b1010010 &
b1010010 '
b1010010 *
b1010001 !
b1010001 $
b1010001 %
b1010001 (
b1010001 )
1"
#4200
0"
#4210
b1010011 &
b1010011 '
b1010011 *
b1010010 !
b1010010 $
b1010010 %
b1010010 (
b1010010 )
1"
#4220
0"
#4230
b1010100 &
b1010100 '
b1010100 *
b1010011 !
b1010011 $
b1010011 %
b1010011 (
b1010011 )
1"
#4240
0"
#4250
b1010101 &
b1010101 '
b1010101 *
b1010100 !
b1010100 $
b1010100 %
b1010100 (
b1010100 )
1"
#4260
0"
#4270
b1010110 &
b1010110 '
b1010110 *
b1010101 !
b1010101 $
b1010101 %
b1010101 (
b1010101 )
1"
#4280
0"
#4290
b1010111 &
b1010111 '
b1010111 *
b1010110 !
b1010110 $
b1010110 %
b1010110 (
b1010110 )
1"
#4300
0"
#4310
b1011000 &
b1011000 '
b1011000 *
b1010111 !
b1010111 $
b1010111 %
b1010111 (
b1010111 )
1"
#4320
0"
#4330
b1011001 &
b1011001 '
b1011001 *
b1011000 !
b1011000 $
b1011000 %
b1011000 (
b1011000 )
1"
#4340
0"
