Computer_Architecture/HDL(Combinational)/Full Adder/FA.v
module fa (
    input wire A,
    input wire B,
    input wire Cin,
    output wire S,
    output wire Co
);

assign S = A^B^Cin;
assign Co = A&B | Cin&(A^B);
    
endmodule

HDL(Combinational)/Full Adder/FA_tb.v
`timescale 1ns/1ns

module fa_tb;

reg A;
reg B;
reg Cin;
wire S;
wire Co;

fa cir(A,B,Cin,S,Co);

initial begin
    $dumpfile("test.vcd");
    $dumpvars(0,fa_tb);

    Cin=0;A=0;B=0;

    #20 B=1;    
    #20 A=1;B=0;
    #20 B=1;
    #20 Cin=1;A=0;B=0;
    #20 B=1;    
    #20 A=1;B=0;    
    #20 B=1;    
    #20;
    $finish;
end

initial begin
    $monitor("Cin=%d|A=%d|B=%d|Co=%d|S=%d",Cin,A,B,Co,S);
end
endmodule

Computer_Architecture/HDL(Combinational)/Full Adder/test.vcd
$date
	Mon May 13 15:57:58 2024
$end
$version
	Icarus Verilog
$end
$timescale
	1ns
$end
$scope module fa_tb $end
$var wire 1 ! S $end
$var wire 1 " Co $end
$var reg 1 # A $end
$var reg 1 $ B $end
$var reg 1 % Cin $end
$scope module cir $end
$var wire 1 # A $end
$var wire 1 $ B $end
$var wire 1 % Cin $end
$var wire 1 " Co $end
$var wire 1 ! S $end
$upscope $end
$upscope $end
$enddefinitions $end
$comment Show the parameter values. $end
$dumpall
$end
#0
$dumpvars
0%
0$
0#
0"
0!
$end
#20
1!
1$
#40
0$
1#
#60
0!
1"
1$
#80
0"
1!
0$
0#
1%
#100
1"
0!
1$
#120
0$
1#
#140
1!
1$
