Antor HDL/combinational/decoder.v
module Decoder(
    input wire [2:0] B,
    input wire E,
    output reg [7:0] D
);


// // Method -> Assignment operator
// assign D[0] = ~B[0] & ~B[1] & ~B[2] & E;
// assign D[1] = B[0] & ~B[1] & ~B[2] & E;
// assign D[2] = ~B[0] & B[1] & ~B[2] & E;
// assign D[3] = B[0] & B[1] & ~B[2] & E;
// assign D[4] = ~B[0] & ~B[1] & B[2] & E;
// assign D[5] = B[0] & ~B[1] & B[2] & E;
// assign D[6] = ~B[0] & B[1] & B[2] & E;
// assign D[7] = B[0] & B[1] & B[2] & E;


// // Method -> If-Else Statement
// always@(*) begin
//     if(E == 1'b0)
//         D = 8'b00000000;
//     else if(B == 3'b000)
//         D = 8'b00000001;
//     else if(B == 3'b001)
//         D = 8'b00000010;
//     else if(B == 3'b010)
//         D = 8'b00000100;
//     else if(B == 3'b011)
//         D = 8'b00001000;
//     else if(B == 3'b100)
//         D = 8'b00010000;
//     else if(B == 3'b101)
//         D = 8'b00100000;
//     else if(B == 3'b110)
//         D = 8'b01000000;
//     else if(B == 3'b111)
//         D = 8'b10000000;
//     else
//         D = 8'b00000000;
// end


// Method -> Case Statement
always@(*) begin
    case({E, B})
        4'b1000: D = 8'b00000001;
        4'b1001: D = 8'b00000010;
        4'b1010: D = 8'b00000100;
        4'b1011: D = 8'b00001000;
        4'b1100: D = 8'b00010000;
        4'b1101: D = 8'b00100000;
        4'b1110: D = 8'b01000000;
        4'b1111: D = 8'b10000000;
        default: D = 8'b00000000;
    endcase
end


endmodule

Computer_Architecture/Antor HDL/combinational/decoder_tb.v
`timescale 1ns/1ps

module Decoder_Tb;
    reg [2:0] B;
    reg E;
    wire [7:0] D;

    Decoder cir1(
        .B(B), 
        .D(D),
        .E(E)
    );

    initial begin

        $dumpfile("Decoder_gtk.vcd");
        $dumpvars;

        E = 0;
        #10;
        E = 1;

        B = 3'b000;
        #10;
        B = 3'b001;
        #10;
        B = 3'b010;
        #10;        
        B = 3'b011;
        #10;        
        B = 3'b100;
        #10;        
        B = 3'b101;
        #10;        
        B = 3'b110;
        #10;
        B = 3'b111;
        #10;

    end

    initial begin
        $monitor("E = %b, B = %3b | D = %8b", E, B, D);
    end

endmodule

Computer_Architecture/Antor HDL/combinational/Decoder_gtk.vcd
$date
	Fri May 24 00:14:48 2024
$end
$version
	Icarus Verilog
$end
$timescale
	1ps
$end
$scope module Decoder_Tb $end
$var wire 8 ! D [7:0] $end
$var reg 3 " B [2:0] $end
$var reg 1 # E $end
$scope module cir1 $end
$var wire 3 $ B [2:0] $end
$var wire 1 # E $end
$var reg 8 % D [7:0] $end
$upscope $end
$upscope $end
$enddefinitions $end
$comment Show the parameter values. $end
$dumpall
$end
#0
$dumpvars
b0 %
bx $
0#
bx "
b0 !
$end
#10000
b1 !
b1 %
b0 "
b0 $
1#
#20000
b10 !
b10 %
b1 "
b1 $
#30000
b100 !
b100 %
b10 "
b10 $
#40000
b1000 !
b1000 %
b11 "
b11 $
#50000
b10000 !
b10000 %
b100 "
b100 $
#60000
b100000 !
b100000 %
b101 "
b101 $
#70000
b1000000 !
b1000000 %
b110 "
b110 $
#80000
b10000000 !
b10000000 %
b111 "
b111 $
