Computer_Architecture/HDL1(Sequential)/Counter/Down Counter Synchronous Methodoloy/sub.v
module subtractor (
    input wire [3:0] I,
    output wire [3:0] O
);
assign O = I - 1;    
endmodule

Computer_Architecture/HDL1(Sequential)/Counter/Down Counter Synchronous Methodoloy/reg.v
module register (
    input wire clk,
    input wire reset,
    input wire [3:0] d,
    output wire [3:0] q
);
reg [3:0] r_reg;
wire [3:0] r_next;
always @(posedge clk,posedge reset) begin
    if(reset)r_reg<=4'b1111;
    else r_reg<=r_next;
end

assign r_next=d;
assign q=r_reg;
endmodule

Computer_Architecture/HDL1(Sequential)/Counter/Down Counter Synchronous Methodoloy/ct.v
module ct (
    input wire clk,
    input wire reset,
    output wire [3:0] q
);

wire [3:0] q_temp,d_temp;
register cir1(clk,reset,d_temp,q_temp);
subtractor cir2(q_temp,d_temp);

assign q= q_temp;
    
endmodule

HDL1(Sequential)/Counter/Down Counter Synchronous Methodoloy/ct_tb.v
`timescale 1ns/1ps

module ct_tb;

reg clk;
reg reset;
wire [3:0] q;

ct circ3(clk,reset,q);

always begin
     clk = ~clk;
    #10;
end

initial begin
    $dumpfile("test.vcd");
    $dumpvars(0,ct_tb);

    clk<=0;
    reset<=1;

    #10;
    reset<=0;

    #10;
    #10;
    #10;
    #10;

end

initial begin
    $monitor("clk=%b|reset=%b|q=%b",clk,reset,q);
end
endmodule

Computer_Architecture/HDL1(Sequential)/Counter/Down Counter Synchronous Methodoloy/test.vcd
$date
	Tue May 14 02:22:49 2024
$end
$version
	Icarus Verilog
$end
$timescale
	1ps
$end
$scope module ct_tb $end
$var wire 4 ! q [3:0] $end
$var reg 1 " clk $end
$var reg 1 # reset $end
$scope module circ3 $end
$var wire 1 " clk $end
$var wire 4 $ q [3:0] $end
$var wire 1 # reset $end
$var wire 4 % q_temp [3:0] $end
$var wire 4 & d_temp [3:0] $end
$scope module cir1 $end
$var wire 1 " clk $end
$var wire 4 ' r_next [3:0] $end
$var wire 1 # reset $end
$var wire 4 ( q [3:0] $end
$var wire 4 ) d [3:0] $end
$var reg 4 * r_reg [3:0] $end
$upscope $end
$scope module cir2 $end
$var wire 4 + I [3:0] $end
$var wire 4 , O [3:0] $end
$upscope $end
$upscope $end
$upscope $end
$enddefinitions $end
$comment Show the parameter values. $end
$dumpall
$end
#0
$dumpvars
b1110 ,
b1111 +
b1111 *
b1110 )
b1111 (
b1110 '
b1110 &
b1111 %
b1111 $
1#
0"
b1111 !
$end
#10000
0#
1"
#20000
0"
#30000
b1101 '
b1101 &
b1101 )
b1101 ,
b1110 !
b1110 $
b1110 %
b1110 (
b1110 *
b1110 +
1"
#40000
0"
#50000
b1100 '
b1100 &
b1100 )
b1100 ,
b1101 !
b1101 $
b1101 %
b1101 (
b1101 *
b1101 +
1"
#60000
0"
#70000
b1011 '
b1011 &
b1011 )
b1011 ,
b1100 !
b1100 $
b1100 %
b1100 (
b1100 *
b1100 +
1"
#80000
0"
#90000
b1010 '
b1010 &
b1010 )
b1010 ,
b1011 !
b1011 $
b1011 %
b1011 (
b1011 *
b1011 +
1"
#100000
0"
#110000
b1001 '
b1001 &
b1001 )
b1001 ,
b1010 !
b1010 $
b1010 %
b1010 (
b1010 *
b1010 +
1"
#120000
0"
#130000
b1000 '
b1000 &
b1000 )
b1000 ,
b1001 !
b1001 $
b1001 %
b1001 (
b1001 *
b1001 +
1"
#140000
0"
#150000
b111 '
b111 &
b111 )
b111 ,
b1000 !
b1000 $
b1000 %
b1000 (
b1000 *
b1000 +
1"
#160000
0"
#170000
b110 '
b110 &
b110 )
b110 ,
b111 !
b111 $
b111 %
b111 (
b111 *
b111 +
1"
#180000
0"
#190000
b101 '
b101 &
b101 )
b101 ,
b110 !
b110 $
b110 %
b110 (
b110 *
b110 +
1"
#200000
0"
#210000
b100 '
b100 &
b100 )
b100 ,
b101 !
b101 $
b101 %
b101 (
b101 *
b101 +
1"
#220000
0"
#230000
b11 '
b11 &
b11 )
b11 ,
b100 !
b100 $
b100 %
b100 (
b100 *
b100 +
1"
#240000
0"
#250000
b10 '
b10 &
b10 )
b10 ,
b11 !
b11 $
b11 %
b11 (
b11 *
b11 +
1"
#260000
0"
#270000
b1 '
b1 &
b1 )
b1 ,
b10 !
b10 $
b10 %
b10 (
b10 *
b10 +
1"
#280000
0"
#290000
b0 '
b0 &
b0 )
b0 ,
b1 !
b1 $
b1 %
b1 (
b1 *
b1 +
1"
#300000
0"
#310000
b1111 '
b1111 &
b1111 )
b1111 ,
b0 !
b0 $
b0 %
b0 (
b0 *
b0 +
1"
#320000
0"
#330000
b1110 '
b1110 &
b1110 )
b1110 ,
b1111 !
b1111 $
b1111 %
b1111 (
b1111 *
b1111 +
1"
#340000
0"
#350000
b1101 '
b1101 &
b1101 )
b1101 ,
b1110 !
b1110 $
b1110 %
b1110 (
b1110 *
b1110 +
1"
#360000
0"
#370000
b1100 '
b1100 &
b1100 )
b1100 ,
b1101 !
b1101 $
b1101 %
b1101 (
b1101 *
b1101 +
1"
#380000
0"
#390000
b1011 '
b1011 &
b1011 )
b1011 ,
b1100 !
b1100 $
b1100 %
b1100 (
b1100 *
b1100 +
1"
#400000
0"
#410000
b1010 '
b1010 &
b1010 )
b1010 ,
b1011 !
b1011 $
b1011 %
b1011 (
b1011 *
b1011 +
1"
#420000
0"
#430000
b1001 '
b1001 &
b1001 )
b1001 ,
b1010 !
b1010 $
b1010 %
b1010 (
b1010 *
b1010 +
1"
#440000
0"
#450000
b1000 '
b1000 &
b1000 )
b1000 ,
b1001 !
b1001 $
b1001 %
b1001 (
b1001 *
b1001 +
1"
#460000
0"
#470000
b111 '
b111 &
b111 )
b111 ,
b1000 !
b1000 $
b1000 %
b1000 (
b1000 *
b1000 +
1"
#480000
0"
#490000
b110 '
b110 &
b110 )
b110 ,
b111 !
b111 $
b111 %
b111 (
b111 *
b111 +
1"
#500000
0"
#510000
b101 '
b101 &
b101 )
b101 ,
b110 !
b110 $
b110 %
b110 (
b110 *
b110 +
1"
#520000
0"
#530000
b100 '
b100 &
b100 )
b100 ,
b101 !
b101 $
b101 %
b101 (
b101 *
b101 +
1"
#540000
0"
#550000
b11 '
b11 &
b11 )
b11 ,
b100 !
b100 $
b100 %
b100 (
b100 *
b100 +
1"
#560000
0"
#570000
b10 '
b10 &
b10 )
b10 ,
b11 !
b11 $
b11 %
b11 (
b11 *
b11 +
1"
#580000
0"
#590000
b1 '
b1 &
b1 )
b1 ,
b10 !
b10 $
b10 %
b10 (
b10 *
b10 +
1"
#600000
0"
#610000
b0 '
b0 &
b0 )
b0 ,
b1 !
b1 $
b1 %
b1 (
b1 *
b1 +
1"
#620000
0"
#630000
b1111 '
b1111 &
b1111 )
b1111 ,
b0 !
b0 $
b0 %
b0 (
b0 *
b0 +
1"
#640000
0"
#650000
b1110 '
b1110 &
b1110 )
b1110 ,
b1111 !
b1111 $
b1111 %
b1111 (
b1111 *
b1111 +
1"
#660000
0"
#670000
b1101 '
b1101 &
b1101 )
b1101 ,
b1110 !
b1110 $
b1110 %
b1110 (
b1110 *
b1110 +
1"
#680000
0"
#690000
b1100 '
b1100 &
b1100 )
b1100 ,
b1101 !
b1101 $
b1101 %
b1101 (
b1101 *
b1101 +
1"
#700000
0"
#710000
b1011 '
b1011 &
b1011 )
b1011 ,
b1100 !
b1100 $
b1100 %
b1100 (
b1100 *
b1100 +
1"
#720000
0"
#730000
b1010 '
b1010 &
b1010 )
b1010 ,
b1011 !
b1011 $
b1011 %
b1011 (
b1011 *
b1011 +
1"
#740000
0"
#750000
b1001 '
b1001 &
b1001 )
b1001 ,
b1010 !
b1010 $
b1010 %
b1010 (
b1010 *
b1010 +
1"
#760000
0"
#770000
b1000 '
b1000 &
b1000 )
b1000 ,
b1001 !
b1001 $
b1001 %
b1001 (
b1001 *
b1001 +
1"
#780000
0"
#790000
b111 '
b111 &
b111 )
b111 ,
b1000 !
b1000 $
b1000 %
b1000 (
b1000 *
b1000 +
1"
#800000
0"
#810000
b110 '
b110 &
b110 )
b110 ,
b111 !
b111 $
b111 %
b111 (
b111 *
b111 +
1"
#820000
0"
#830000
b101 '
b101 &
b101 )
b101 ,
b110 !
b110 $
b110 %
b110 (
b110 *
b110 +
1"
#840000
0"
#850000
b100 '
b100 &
b100 )
b100 ,
b101 !
b101 $
b101 %
b101 (
b101 *
b101 +
1"
#860000
0"
#870000
b11 '
b11 &
b11 )
b11 ,
b100 !
b100 $
b100 %
b100 (
b100 *
b100 +
1"
#880000
0"
#890000
b10 '
b10 &
b10 )
b10 ,
b11 !
b11 $
b11 %
b11 (
b11 *
b11 +
1"
#900000
0"
#910000
b1 '
b1 &
b1 )
b1 ,
b10 !
b10 $
b10 %
b10 (
b10 *
b10 +
1"
#920000
0"
#930000
b0 '
b0 &
b0 )
b0 ,
b1 !
b1 $
b1 %
b1 (
b1 *
b1 +
1"
#940000
0"
#950000
b1111 '
b1111 &
b1111 )
b1111 ,
b0 !
b0 $
b0 %
b0 (
b0 *
b0 +
1"
#960000
0"
#970000
b1110 '
b1110 &
b1110 )
b1110 ,
b1111 !
b1111 $
b1111 %
b1111 (
b1111 *
b1111 +
1"
#980000
0"
#990000
b1101 '
b1101 &
b1101 )
b1101 ,
b1110 !
b1110 $
b1110 %
b1110 (
b1110 *
b1110 +
1"
#1000000
0"
#1010000
b1100 '
b1100 &
b1100 )
b1100 ,
b1101 !
b1101 $
b1101 %
b1101 (
b1101 *
b1101 +
1"
#1020000
0"
#1030000
b1011 '
b1011 &
b1011 )
b1011 ,
b1100 !
b1100 $
b1100 %
b1100 (
b1100 *
b1100 +
1"
#1040000
0"
#1050000
b1010 '
b1010 &
b1010 )
b1010 ,
b1011 !
b1011 $
b1011 %
b1011 (
b1011 *
b1011 +
1"
#1060000
0"
#1070000
b1001 '
b1001 &
b1001 )
b1001 ,
b1010 !
b1010 $
b1010 %
b1010 (
b1010 *
b1010 +
1"
#1080000
0"
#1090000
b1000 '
b1000 &
b1000 )
b1000 ,
b1001 !
b1001 $
b1001 %
b1001 (
b1001 *
b1001 +
1"
#1100000
0"
#1110000
b111 '
b111 &
b111 )
b111 ,
b1000 !
b1000 $
b1000 %
b1000 (
b1000 *
b1000 +
1"
#1120000
0"
#1130000
b110 '
b110 &
b110 )
b110 ,
b111 !
b111 $
b111 %
b111 (
b111 *
b111 +
1"
#1140000
0"
#1150000
b101 '
b101 &
b101 )
b101 ,
b110 !
b110 $
b110 %
b110 (
b110 *
b110 +
1"
#1160000
0"
#1170000
b100 '
b100 &
b100 )
b100 ,
b101 !
b101 $
b101 %
b101 (
b101 *
b101 +
1"
#1180000
0"
#1190000
b11 '
b11 &
b11 )
b11 ,
b100 !
b100 $
b100 %
b100 (
b100 *
b100 +
1"
#1200000
0"
#1210000
b10 '
b10 &
b10 )
b10 ,
b11 !
b11 $
b11 %
b11 (
b11 *
b11 +
1"
#1220000
0"
#1230000
b1 '
b1 &
b1 )
b1 ,
b10 !
b10 $
b10 %
b10 (
b10 *
b10 +
1"
#1240000
0"
#1250000
b0 '
b0 &
b0 )
b0 ,
b1 !
b1 $
b1 %
b1 (
b1 *
b1 +
1"
#1260000
0"
#1270000
b1111 '
b1111 &
b1111 )
b1111 ,
b0 !
b0 $
b0 %
b0 (
b0 *
b0 +
1"
#1280000
0"
#1290000
b1110 '
b1110 &
b1110 )
b1110 ,
b1111 !
b1111 $
b1111 %
b1111 (
b1111 *
b1111 +
1"
#1300000
0"
#1310000
b1101 '
b1101 &
b1101 )
b1101 ,
b1110 !
b1110 $
b1110 %
b1110 (
b1110 *
b1110 +
1"
#1320000
0"
#1330000
b1100 '
b1100 &
b1100 )
b1100 ,
b1101 !
b1101 $
b1101 %
b1101 (
b1101 *
b1101 +
1"
#1340000
0"
#1350000
b1011 '
b1011 &
b1011 )
b1011 ,
b1100 !
b1100 $
b1100 %
b1100 (
b1100 *
b1100 +
1"
#1360000
0"
#1370000
b1010 '
b1010 &
b1010 )
b1010 ,
b1011 !
b1011 $
b1011 %
b1011 (
b1011 *
b1011 +
1"
#1380000
0"
#1390000
b1001 '
b1001 &
b1001 )
b1001 ,
b1010 !
b1010 $
b1010 %
b1010 (
b1010 *
b1010 +
1"
#1400000
0"
#1410000
b1000 '
b1000 &
b1000 )
b1000 ,
b1001 !
b1001 $
b1001 %
b1001 (
b1001 *
b1001 +
1"
#1420000
0"
#1430000
b111 '
b111 &
b111 )
b111 ,
b1000 !
b1000 $
b1000 %
b1000 (
b1000 *
b1000 +
1"
#1440000
0"
#1450000
b110 '
b110 &
b110 )
b110 ,
b111 !
b111 $
b111 %
b111 (
b111 *
b111 +
1"
#1460000
0"
#1470000
b101 '
b101 &
b101 )
b101 ,
b110 !
b110 $
b110 %
b110 (
b110 *
b110 +
1"
#1480000
0"
#1490000
b100 '
b100 &
b100 )
b100 ,
b101 !
b101 $
b101 %
b101 (
b101 *
b101 +
1"
#1500000
0"
#1510000
b11 '
b11 &
b11 )
b11 ,
b100 !
b100 $
b100 %
b100 (
b100 *
b100 +
1"
#1520000
0"
#1530000
b10 '
b10 &
b10 )
b10 ,
b11 !
b11 $
b11 %
b11 (
b11 *
b11 +
1"
#1540000
0"
#1550000
b1 '
b1 &
b1 )
b1 ,
b10 !
b10 $
b10 %
b10 (
b10 *
b10 +
1"
#1560000
0"
#1570000
b0 '
b0 &
b0 )
b0 ,
b1 !
b1 $
b1 %
b1 (
b1 *
b1 +
1"
#1580000
0"
#1590000
b1111 '
b1111 &
b1111 )
b1111 ,
b0 !
b0 $
b0 %
b0 (
b0 *
b0 +
1"
#1600000
0"
#1610000
b1110 '
b1110 &
b1110 )
b1110 ,
b1111 !
b1111 $
b1111 %
b1111 (
b1111 *
b1111 +
1"
#1620000
0"
#1630000
b1101 '
b1101 &
b1101 )
b1101 ,
b1110 !
b1110 $
b1110 %
b1110 (
b1110 *
b1110 +
1"
#1640000
0"
#1650000
b1100 '
b1100 &
b1100 )
b1100 ,
b1101 !
b1101 $
b1101 %
b1101 (
b1101 *
b1101 +
1"
#1660000
0"
#1670000
b1011 '
b1011 &
b1011 )
b1011 ,
b1100 !
b1100 $
b1100 %
b1100 (
b1100 *
b1100 +
1"
#1680000
0"
#1690000
b1010 '
b1010 &
b1010 )
b1010 ,
b1011 !
b1011 $
b1011 %
b1011 (
b1011 *
b1011 +
1"
#1700000
0"
#1710000
b1001 '
b1001 &
b1001 )
b1001 ,
b1010 !
b1010 $
b1010 %
b1010 (
b1010 *
b1010 +
1"
#1720000
0"
#1730000
b1000 '
b1000 &
b1000 )
b1000 ,
b1001 !
b1001 $
b1001 %
b1001 (
b1001 *
b1001 +
1"
#1740000
0"
#1750000
b111 '
b111 &
b111 )
b111 ,
b1000 !
b1000 $
b1000 %
b1000 (
b1000 *
b1000 +
1"
#1760000
0"
#1770000
b110 '
b110 &
b110 )
b110 ,
b111 !
b111 $
b111 %
b111 (
b111 *
b111 +
1"
#1780000
0"
#1790000
b101 '
b101 &
b101 )
b101 ,
b110 !
b110 $
b110 %
b110 (
b110 *
b110 +
1"
#1800000
0"
#1810000
b100 '
b100 &
b100 )
b100 ,
b101 !
b101 $
b101 %
b101 (
b101 *
b101 +
1"
#1820000
0"
#1830000
b11 '
b11 &
b11 )
b11 ,
b100 !
b100 $
b100 %
b100 (
b100 *
b100 +
1"
#1840000
0"
#1850000
b10 '
b10 &
b10 )
b10 ,
b11 !
b11 $
b11 %
b11 (
b11 *
b11 +
1"
#1860000
0"
#1870000
b1 '
b1 &
b1 )
b1 ,
b10 !
b10 $
b10 %
b10 (
b10 *
b10 +
1"
#1880000
0"
#1890000
b0 '
b0 &
b0 )
b0 ,
b1 !
b1 $
b1 %
b1 (
b1 *
b1 +
1"
#1900000
0"
#1910000
b1111 '
b1111 &
b1111 )
b1111 ,
b0 !
b0 $
b0 %
b0 (
b0 *
b0 +
1"
#1920000
0"
#1930000
b1110 '
b1110 &
b1110 )
b1110 ,
b1111 !
b1111 $
b1111 %
b1111 (
b1111 *
b1111 +
1"
#1940000
0"
#1950000
b1101 '
b1101 &
b1101 )
b1101 ,
b1110 !
b1110 $
b1110 %
b1110 (
b1110 *
b1110 +
1"
#1960000
0"
#1970000
b1100 '
b1100 &
b1100 )
b1100 ,
b1101 !
b1101 $
b1101 %
b1101 (
b1101 *
b1101 +
1"
#1980000
0"
#1990000
b1011 '
b1011 &
b1011 )
b1011 ,
b1100 !
b1100 $
b1100 %
b1100 (
b1100 *
b1100 +
1"
#2000000
0"
#2010000
b1010 '
b1010 &
b1010 )
b1010 ,
b1011 !
b1011 $
b1011 %
b1011 (
b1011 *
b1011 +
1"
#2020000
0"
#2030000
b1001 '
b1001 &
b1001 )
b1001 ,
b1010 !
b1010 $
b1010 %
b1010 (
b1010 *
b1010 +
1"
#2040000
0"
#2050000
b1000 '
b1000 &
b1000 )
b1000 ,
b1001 !
b1001 $
b1001 %
b1001 (
b1001 *
b1001 +
1"
#2060000
0"
#2070000
b111 '
b111 &
b111 )
b111 ,
b1000 !
b1000 $
b1000 %
b1000 (
b1000 *
b1000 +
1"
#2080000
0"
#2090000
b110 '
b110 &
b110 )
b110 ,
b111 !
b111 $
b111 %
b111 (
b111 *
b111 +
1"
#2100000
0"
#2110000
b101 '
b101 &
b101 )
b101 ,
b110 !
b110 $
b110 %
b110 (
b110 *
b110 +
1"
#2120000
0"
#2130000
b100 '
b100 &
b100 )
b100 ,
b101 !
b101 $
b101 %
b101 (
b101 *
b101 +
1"
#2140000
0"
#2150000
b11 '
b11 &
b11 )
b11 ,
b100 !
b100 $
b100 %
b100 (
b100 *
b100 +
1"
#2160000
0"
#2170000
b10 '
b10 &
b10 )
b10 ,
b11 !
b11 $
b11 %
b11 (
b11 *
b11 +
1"
#2180000
0"
#2190000
b1 '
b1 &
b1 )
b1 ,
b10 !
b10 $
b10 %
b10 (
b10 *
b10 +
1"
#2200000
0"
#2210000
b0 '
b0 &
b0 )
b0 ,
b1 !
b1 $
b1 %
b1 (
b1 *
b1 +
1"
#2220000
0"
#2230000
b1111 '
b1111 &
b1111 )
b1111 ,
b0 !
b0 $
b0 %
b0 (
b0 *
b0 +
1"
#2240000
0"
#2250000
b1110 '
b1110 &
b1110 )
b1110 ,
b1111 !
b1111 $
b1111 %
b1111 (
b1111 *
b1111 +
1"
#2260000
0"
#2270000
b1101 '
b1101 &
b1101 )
b1101 ,
b1110 !
b1110 $
b1110 %
b1110 (
b1110 *
b1110 +
1"
#2280000
0"
#2290000
b1100 '
b1100 &
b1100 )
b1100 ,
b1101 !
b1101 $
b1101 %
b1101 (
b1101 *
b1101 +
1"
#2300000
0"
#2310000
b1011 '
b1011 &
b1011 )
b1011 ,
b1100 !
b1100 $
b1100 %
b1100 (
b1100 *
b1100 +
1"
#2320000
0"
#2330000
b1010 '
b1010 &
b1010 )
b1010 ,
b1011 !
b1011 $
b1011 %
b1011 (
b1011 *
b1011 +
1"
#2340000
0"
#2350000
b1001 '
b1001 &
b1001 )
b1001 ,
b1010 !
b1010 $
b1010 %
b1010 (
b1010 *
b1010 +
1"
#2360000
0"
#2370000
b1000 '
b1000 &
b1000 )
b1000 ,
b1001 !
b1001 $
b1001 %
b1001 (
b1001 *
b1001 +
1"
#2380000
0"
#2390000
b111 '
b111 &
b111 )
b111 ,
b1000 !
b1000 $
b1000 %
b1000 (
b1000 *
b1000 +
1"
#2400000
0"
#2410000
b110 '
b110 &
b110 )
b110 ,
b111 !
b111 $
b111 %
b111 (
b111 *
b111 +
1"
#2420000
0"
#2430000
b101 '
b101 &
b101 )
b101 ,
b110 !
b110 $
b110 %
b110 (
b110 *
b110 +
1"
#2440000
0"
#2450000
b100 '
b100 &
b100 )
b100 ,
b101 !
b101 $
b101 %
b101 (
b101 *
b101 +
1"
#2460000
0"
#2470000
b11 '
b11 &
b11 )
b11 ,
b100 !
b100 $
b100 %
b100 (
b100 *
b100 +
1"
#2480000
0"
#2490000
b10 '
b10 &
b10 )
b10 ,
b11 !
b11 $
b11 %
b11 (
b11 *
b11 +
1"
#2500000
0"
#2510000
b1 '
b1 &
b1 )
b1 ,
b10 !
b10 $
b10 %
b10 (
b10 *
b10 +
1"
#2520000
0"
#2530000
b0 '
b0 &
b0 )
b0 ,
b1 !
b1 $
b1 %
b1 (
b1 *
b1 +
1"
#2540000
0"
#2550000
b1111 '
b1111 &
b1111 )
b1111 ,
b0 !
b0 $
b0 %
b0 (
b0 *
b0 +
1"
#2560000
0"
#2570000
b1110 '
b1110 &
b1110 )
b1110 ,
b1111 !
b1111 $
b1111 %
b1111 (
b1111 *
b1111 +
1"
#2580000
0"
#2590000
b1101 '
b1101 &
b1101 )
b1101 ,
b1110 !
b1110 $
b1110 %
b1110 (
b1110 *
b1110 +
1"
#2600000
0"
#2610000
b1100 '
b1100 &
b1100 )
b1100 ,
b1101 !
b1101 $
b1101 %
b1101 (
b1101 *
b1101 +
1"
#2620000
0"
#2630000
b1011 '
b1011 &
b1011 )
b1011 ,
b1100 !
b1100 $
b1100 %
b1100 (
b1100 *
b1100 +
1"
#2640000
0"
#2650000
b1010 '
b1010 &
b1010 )
b1010 ,
b1011 !
b1011 $
b1011 %
b1011 (
b1011 *
b1011 +
1"
#2660000
0"
#2670000
b1001 '
b1001 &
b1001 )
b1001 ,
b1010 !
b1010 $
b1010 %
b1010 (
b1010 *
b1010 +
1"
#2680000
0"
#2690000
b1000 '
b1000 &
b1000 )
b1000 ,
b1001 !
b1001 $
b1001 %
b1001 (
b1001 *
b1001 +
1"
#2700000
0"
#2710000
b111 '
b111 &
b111 )
b111 ,
b1000 !
b1000 $
b1000 %
b1000 (
b1000 *
b1000 +
1"
#2720000
0"
#2730000
b110 '
b110 &
b110 )
b110 ,
b111 !
b111 $
b111 %
b111 (
b111 *
b111 +
1"
#2740000
0"
#2750000
b101 '
b101 &
b101 )
b101 ,
b110 !
b110 $
b110 %
b110 (
b110 *
b110 +
1"
#2760000
0"
#2770000
b100 '
b100 &
b100 )
b100 ,
b101 !
b101 $
b101 %
b101 (
b101 *
b101 +
1"
#2780000
0"
#2790000
b11 '
b11 &
b11 )
b11 ,
b100 !
b100 $
b100 %
b100 (
b100 *
b100 +
1"
#2800000
0"
#2810000
b10 '
b10 &
b10 )
b10 ,
b11 !
b11 $
b11 %
b11 (
b11 *
b11 +
1"
#2820000
0"
#2830000
b1 '
b1 &
b1 )
b1 ,
b10 !
b10 $
b10 %
b10 (
b10 *
b10 +
1"
#2840000
0"
#2850000
b0 '
b0 &
b0 )
b0 ,
b1 !
b1 $
b1 %
b1 (
b1 *
b1 +
1"
#2860000
0"
#2870000
b1111 '
b1111 &
b1111 )
b1111 ,
b0 !
b0 $
b0 %
b0 (
b0 *
b0 +
1"
#2880000
0"
#2890000
b1110 '
b1110 &
b1110 )
b1110 ,
b1111 !
b1111 $
b1111 %
b1111 (
b1111 *
b1111 +
1"
#2900000
0"
#2910000
b1101 '
b1101 &
b1101 )
b1101 ,
b1110 !
b1110 $
b1110 %
b1110 (
b1110 *
b1110 +
1"
#2920000
0"
#2930000
b1100 '
b1100 &
b1100 )
b1100 ,
b1101 !
b1101 $
b1101 %
b1101 (
b1101 *
b1101 +
1"
#2940000
0"
#2950000
b1011 '
b1011 &
b1011 )
b1011 ,
b1100 !
b1100 $
b1100 %
b1100 (
b1100 *
b1100 +
1"
#2960000
0"
#2970000
b1010 '
b1010 &
b1010 )
b1010 ,
b1011 !
b1011 $
b1011 %
b1011 (
b1011 *
b1011 +
1"
#2980000
0"
#2990000
b1001 '
b1001 &
b1001 )
b1001 ,
b1010 !
b1010 $
b1010 %
b1010 (
b1010 *
b1010 +
1"
#3000000
0"
#3010000
b1000 '
b1000 &
b1000 )
b1000 ,
b1001 !
b1001 $
b1001 %
b1001 (
b1001 *
b1001 +
1"
#3020000
0"
#3030000
b111 '
b111 &
b111 )
b111 ,
b1000 !
b1000 $
b1000 %
b1000 (
b1000 *
b1000 +
1"
#3040000
0"
#3050000
b110 '
b110 &
b110 )
b110 ,
b111 !
b111 $
b111 %
b111 (
b111 *
b111 +
1"
#3060000
0"
#3070000
b101 '
b101 &
b101 )
b101 ,
b110 !
b110 $
b110 %
b110 (
b110 *
b110 +
1"
#3080000
0"
#3090000
b100 '
b100 &
b100 )
b100 ,
b101 !
b101 $
b101 %
b101 (
b101 *
b101 +
1"
#3100000
0"
#3110000
b11 '
b11 &
b11 )
b11 ,
b100 !
b100 $
b100 %
b100 (
b100 *
b100 +
1"
#3120000
0"
#3130000
b10 '
b10 &
b10 )
b10 ,
b11 !
b11 $
b11 %
b11 (
b11 *
b11 +
1"
#3140000
0"
#3150000
b1 '
b1 &
b1 )
b1 ,
b10 !
b10 $
b10 %
b10 (
b10 *
b10 +
1"
#3160000
0"
#3170000
b0 '
b0 &
b0 )
b0 ,
b1 !
b1 $
b1 %
b1 (
b1 *
b1 +
1"
#3180000
0"
#3190000
b1111 '
b1111 &
b1111 )
b1111 ,
b0 !
b0 $
b0 %
b0 (
b0 *
b0 +
1"
#3200000
0"
#3210000
b1110 '
b1110 &
b1110 )
b1110 ,
b1111 !
b1111 $
b1111 %
b1111 (
b1111 *
b1111 +
1"
#3220000
0"
#3230000
b1101 '
b1101 &
b1101 )
b1101 ,
b1110 !
b1110 $
b1110 %
b1110 (
b1110 *
b1110 +
1"
#3240000
0"
#3250000
b1100 '
b1100 &
b1100 )
b1100 ,
b1101 !
b1101 $
b1101 %
b1101 (
b1101 *
b1101 +
1"
#3260000
0"
#3270000
b1011 '
b1011 &
b1011 )
b1011 ,
b1100 !
b1100 $
b1100 %
b1100 (
b1100 *
b1100 +
1"
#3280000
0"
#3290000
b1010 '
b1010 &
b1010 )
b1010 ,
b1011 !
b1011 $
b1011 %
b1011 (
b1011 *
b1011 +
1"
#3300000
0"
#3310000
b1001 '
b1001 &
b1001 )
b1001 ,
b1010 !
b1010 $
b1010 %
b1010 (
b1010 *
b1010 +
1"
#3320000
0"
#3330000
b1000 '
b1000 &
b1000 )
b1000 ,
b1001 !
b1001 $
b1001 %
b1001 (
b1001 *
b1001 +
1"
#3340000
0"
#3350000
b111 '
b111 &
b111 )
b111 ,
b1000 !
b1000 $
b1000 %
b1000 (
b1000 *
b1000 +
1"
#3360000
0"
#3370000
b110 '
b110 &
b110 )
b110 ,
b111 !
b111 $
b111 %
b111 (
b111 *
b111 +
1"
#3380000
0"
#3390000
b101 '
b101 &
b101 )
b101 ,
b110 !
b110 $
b110 %
b110 (
b110 *
b110 +
1"
#3400000
0"
#3410000
b100 '
b100 &
b100 )
b100 ,
b101 !
b101 $
b101 %
b101 (
b101 *
b101 +
1"
#3420000
0"
#3430000
b11 '
b11 &
b11 )
b11 ,
b100 !
b100 $
b100 %
b100 (
b100 *
b100 +
1"
#3440000
0"
#3450000
b10 '
b10 &
b10 )
b10 ,
b11 !
b11 $
b11 %
b11 (
b11 *
b11 +
1"
#3460000
0"
#3470000
b1 '
b1 &
b1 )
b1 ,
b10 !
b10 $
b10 %
b10 (
b10 *
b10 +
1"
#3480000
0"
#3490000
b0 '
b0 &
b0 )
b0 ,
b1 !
b1 $
b1 %
b1 (
b1 *
b1 +
1"
#3500000
0"
#3510000
b1111 '
b1111 &
b1111 )
b1111 ,
b0 !
b0 $
b0 %
b0 (
b0 *
b0 +
1"
#3520000
0"
#3530000
b1110 '
b1110 &
b1110 )
b1110 ,
b1111 !
b1111 $
b1111 %
b1111 (
b1111 *
b1111 +
1"
#3540000
0"
#3550000
b1101 '
b1101 &
b1101 )
b1101 ,
b1110 !
b1110 $
b1110 %
b1110 (
b1110 *
b1110 +
1"
#3560000
0"
#3570000
b1100 '
b1100 &
b1100 )
b1100 ,
b1101 !
b1101 $
b1101 %
b1101 (
b1101 *
b1101 +
1"
#3580000
0"
#3590000
b1011 '
b1011 &
b1011 )
b1011 ,
b1100 !
b1100 $
b1100 %
b1100 (
b1100 *
b1100 +
1"
#3600000
0"
#3610000
b1010 '
b1010 &
b1010 )
b1010 ,
b1011 !
b1011 $
b1011 %
b1011 (
b1011 *
b1011 +
1"
#3620000
0"
#3630000
b1001 '
b1001 &
b1001 )
b1001 ,
b1010 !
b1010 $
b1010 %
b1010 (
b1010 *
b1010 +
1"
#3640000
0"
#3650000
b1000 '
b1000 &
b1000 )
b1000 ,
b1001 !
b1001 $
b1001 %
b1001 (
b1001 *
b1001 +
1"
#3660000
0"
#3670000
b111 '
b111 &
b111 )
b111 ,
b1000 !
b1000 $
b1000 %
b1000 (
b1000 *
b1000 +
1"
#3680000
0"
#3690000
b110 '
b110 &
b110 )
b110 ,
b111 !
b111 $
b111 %
b111 (
b111 *
b111 +
1"
#3700000
0"
#3710000
b101 '
b101 &
b101 )
b101 ,
b110 !
b110 $
b110 %
b110 (
b110 *
b110 +
1"
#3720000
0"
#3730000
b100 '
b100 &
b100 )
b100 ,
b101 !
b101 $
b101 %
b101 (
b101 *
b101 +
1"
#3740000
0"
#3750000
b11 '
b11 &
b11 )
b11 ,
b100 !
b100 $
b100 %
b100 (
b100 *
b100 +
1"
#3760000
0"
#3770000
b10 '
b10 &
b10 )
b10 ,
b11 !
b11 $
b11 %
b11 (
b11 *
b11 +
1"
#3780000
0"
#3790000
b1 '
b1 &
b1 )
b1 ,
b10 !
b10 $
b10 %
b10 (
b10 *
b10 +
1"
#3800000
0"
#3810000
b0 '
b0 &
b0 )
b0 ,
b1 !
b1 $
b1 %
b1 (
b1 *
b1 +
1"
#3820000
0"
#3830000
b1111 '
b1111 &
b1111 )
b1111 ,
b0 !
b0 $
b0 %
b0 (
b0 *
b0 +
1"
#3840000
0"
#3850000
b1110 '
b1110 &
b1110 )
b1110 ,
b1111 !
b1111 $
b1111 %
b1111 (
b1111 *
b1111 +
1"
#3860000
0"
