Computer_Architecture/HDL1(Sequential)/Counter/Down Counter Synchronous Methodoloy/sub.v
module subtractor (
    input wire [3:0] I,
    output wire [3:0] O
);
assign O = I - 1;    
endmodule

Computer_Architecture/HDL1(Sequential)/Counter/4bit Down Counter/register.v
module register (
    input wire clk,
    input wire reset,
    input wire [3:0] d,
    output reg [3:0] q
);

always @(posedge clk,posedge reset) begin
    if(reset) q<=4'b1111;
    else q<=d;
end    
endmodule

Computer_Architecture/HDL1(Sequential)/Counter/4bit Down Counter/counter.v
module counter (
    input wire clk,
    input wire reset,
    output wire [3:0] q
);

wire [3:0] q_temp,d_temp;
register circ1(clk,reset,d_temp,q_temp);
subtractor circ2(q_temp,d_temp);

assign q = q_temp;
    
endmodule

HDL1(Sequential)/Counter/4bit Down Counter/counter_tb.v
`timescale 1ns/1ns

module counter_tb;

reg clk;
reg reset;
wire [3:0] q;

counter circ(clk,reset,q);

always begin
    clk = ~clk;
    #10;
end

initial begin
    $dumpfile("test.vcd");
    $dumpvars(0,counter_tb);

    clk<=0;
    reset<=1;
    #20;
    reset<=0;
    #20;
end

initial begin
    $monitor("clk=%b,reset=%b,q=%b",clk,reset,q);
end
endmodule

Computer_Architecture/HDL1(Sequential)/Counter/4bit Down Counter/test.vcd
$date
	Mon May 13 15:24:32 2024
$end
$version
	Icarus Verilog
$end
$timescale
	1ns
$end
$scope module counter_tb $end
$var wire 4 ! q [3:0] $end
$var reg 1 " clk $end
$var reg 1 # reset $end
$scope module circ $end
$var wire 1 " clk $end
$var wire 4 $ q [3:0] $end
$var wire 1 # reset $end
$var wire 4 % q_temp [3:0] $end
$var wire 4 & d_temp [3:0] $end
$scope module circ1 $end
$var wire 1 " clk $end
$var wire 1 # reset $end
$var wire 4 ' d [3:0] $end
$var reg 4 ( q [3:0] $end
$upscope $end
$scope module circ2 $end
$var wire 4 ) I [3:0] $end
$var wire 4 * O [3:0] $end
$upscope $end
$upscope $end
$upscope $end
$enddefinitions $end
$comment Show the parameter values. $end
$dumpall
$end
#0
$dumpvars
b1110 *
b1111 )
b1111 (
b1110 '
b1110 &
b1111 %
b1111 $
1#
0"
b1111 !
$end
#10
1"
#20
0#
0"
#30
b1101 &
b1101 '
b1101 *
b1110 !
b1110 $
b1110 %
b1110 (
b1110 )
1"
#40
0"
#50
b1100 &
b1100 '
b1100 *
b1101 !
b1101 $
b1101 %
b1101 (
b1101 )
1"
#60
0"
#70
b1011 &
b1011 '
b1011 *
b1100 !
b1100 $
b1100 %
b1100 (
b1100 )
1"
#80
0"
#90
b1010 &
b1010 '
b1010 *
b1011 !
b1011 $
b1011 %
b1011 (
b1011 )
1"
#100
0"
#110
b1001 &
b1001 '
b1001 *
b1010 !
b1010 $
b1010 %
b1010 (
b1010 )
1"
#120
0"
#130
b1000 &
b1000 '
b1000 *
b1001 !
b1001 $
b1001 %
b1001 (
b1001 )
1"
#140
0"
#150
b111 &
b111 '
b111 *
b1000 !
b1000 $
b1000 %
b1000 (
b1000 )
1"
#160
0"
#170
b110 &
b110 '
b110 *
b111 !
b111 $
b111 %
b111 (
b111 )
1"
#180
0"
#190
b101 &
b101 '
b101 *
b110 !
b110 $
b110 %
b110 (
b110 )
1"
#200
0"
#210
b100 &
b100 '
b100 *
b101 !
b101 $
b101 %
b101 (
b101 )
1"
#220
0"
#230
b11 &
b11 '
b11 *
b100 !
b100 $
b100 %
b100 (
b100 )
1"
#240
0"
#250
b10 &
b10 '
b10 *
b11 !
b11 $
b11 %
b11 (
b11 )
1"
#260
0"
#270
b1 &
b1 '
b1 *
b10 !
b10 $
b10 %
b10 (
b10 )
1"
#280
0"
#290
b0 &
b0 '
b0 *
b1 !
b1 $
b1 %
b1 (
b1 )
1"
#300
0"
#310
b1111 &
b1111 '
b1111 *
b0 !
b0 $
b0 %
b0 (
b0 )
1"
#320
0"
#330
b1110 &
b1110 '
b1110 *
b1111 !
b1111 $
b1111 %
b1111 (
b1111 )
1"
#340
0"
#350
b1101 &
b1101 '
b1101 *
b1110 !
b1110 $
b1110 %
b1110 (
b1110 )
1"
#360
0"
#370
b1100 &
b1100 '
b1100 *
b1101 !
b1101 $
b1101 %
b1101 (
b1101 )
1"
#380
0"
#390
b1011 &
b1011 '
b1011 *
b1100 !
b1100 $
b1100 %
b1100 (
b1100 )
1"
#400
0"
#410
b1010 &
b1010 '
b1010 *
b1011 !
b1011 $
b1011 %
b1011 (
b1011 )
1"
#420
0"
#430
b1001 &
b1001 '
b1001 *
b1010 !
b1010 $
b1010 %
b1010 (
b1010 )
1"
#440
0"
#450
b1000 &
b1000 '
b1000 *
b1001 !
b1001 $
b1001 %
b1001 (
b1001 )
1"
#460
0"
#470
b111 &
b111 '
b111 *
b1000 !
b1000 $
b1000 %
b1000 (
b1000 )
1"
#480
0"
#490
b110 &
b110 '
b110 *
b111 !
b111 $
b111 %
b111 (
b111 )
1"
#500
0"
#510
b101 &
b101 '
b101 *
b110 !
b110 $
b110 %
b110 (
b110 )
1"
#520
0"
#530
b100 &
b100 '
b100 *
b101 !
b101 $
b101 %
b101 (
b101 )
1"
#540
0"
#550
b11 &
b11 '
b11 *
b100 !
b100 $
b100 %
b100 (
b100 )
1"
#560
0"
#570
b10 &
b10 '
b10 *
b11 !
b11 $
b11 %
b11 (
b11 )
1"
#580
0"
#590
b1 &
b1 '
b1 *
b10 !
b10 $
b10 %
b10 (
b10 )
1"
#600
0"
#610
b0 &
b0 '
b0 *
b1 !
b1 $
b1 %
b1 (
b1 )
1"
#620
0"
#630
b1111 &
b1111 '
b1111 *
b0 !
b0 $
b0 %
b0 (
b0 )
1"
#640
0"
#650
b1110 &
b1110 '
b1110 *
b1111 !
b1111 $
b1111 %
b1111 (
b1111 )
1"
#660
0"
#670
b1101 &
b1101 '
b1101 *
b1110 !
b1110 $
b1110 %
b1110 (
b1110 )
1"
#680
0"
#690
b1100 &
b1100 '
b1100 *
b1101 !
b1101 $
b1101 %
b1101 (
b1101 )
1"
#700
0"
#710
b1011 &
b1011 '
b1011 *
b1100 !
b1100 $
b1100 %
b1100 (
b1100 )
1"
#720
0"
#730
b1010 &
b1010 '
b1010 *
b1011 !
b1011 $
b1011 %
b1011 (
b1011 )
1"
#740
0"
#750
b1001 &
b1001 '
b1001 *
b1010 !
b1010 $
b1010 %
b1010 (
b1010 )
1"
#760
0"
#770
b1000 &
b1000 '
b1000 *
b1001 !
b1001 $
b1001 %
b1001 (
b1001 )
1"
#780
0"
#790
b111 &
b111 '
b111 *
b1000 !
b1000 $
b1000 %
b1000 (
b1000 )
1"
#800
0"
#810
b110 &
b110 '
b110 *
b111 !
b111 $
b111 %
b111 (
b111 )
1"
#820
0"
#830
b101 &
b101 '
b101 *
b110 !
b110 $
b110 %
b110 (
b110 )
1"
#840
0"
#850
b100 &
b100 '
b100 *
b101 !
b101 $
b101 %
b101 (
b101 )
1"
#860
0"
#870
b11 &
b11 '
b11 *
b100 !
b100 $
b100 %
b100 (
b100 )
1"
#880
0"
#890
b10 &
b10 '
b10 *
b11 !
b11 $
b11 %
b11 (
b11 )
1"
#900
0"
#910
b1 &
b1 '
b1 *
b10 !
b10 $
b10 %
b10 (
b10 )
1"
#920
0"
#930
b0 &
b0 '
b0 *
b1 !
b1 $
b1 %
b1 (
b1 )
1"
#940
0"
#950
b1111 &
b1111 '
b1111 *
b0 !
b0 $
b0 %
b0 (
b0 )
1"
#960
0"
#970
b1110 &
b1110 '
b1110 *
b1111 !
b1111 $
b1111 %
b1111 (
b1111 )
1"
#980
0"
#990
b1101 &
b1101 '
b1101 *
b1110 !
b1110 $
b1110 %
b1110 (
b1110 )
1"
#1000
0"
#1010
b1100 &
b1100 '
b1100 *
b1101 !
b1101 $
b1101 %
b1101 (
b1101 )
1"
#1020
0"
#1030
b1011 &
b1011 '
b1011 *
b1100 !
b1100 $
b1100 %
b1100 (
b1100 )
1"
#1040
0"
#1050
b1010 &
b1010 '
b1010 *
b1011 !
b1011 $
b1011 %
b1011 (
b1011 )
1"
#1060
0"
#1070
b1001 &
b1001 '
b1001 *
b1010 !
b1010 $
b1010 %
b1010 (
b1010 )
1"
#1080
0"
#1090
b1000 &
b1000 '
b1000 *
b1001 !
b1001 $
b1001 %
b1001 (
b1001 )
1"
#1100
0"
#1110
b111 &
b111 '
b111 *
b1000 !
b1000 $
b1000 %
b1000 (
b1000 )
1"
#1120
0"
#1130
b110 &
b110 '
b110 *
b111 !
b111 $
b111 %
b111 (
b111 )
1"
#1140
0"
#1150
b101 &
b101 '
b101 *
b110 !
b110 $
b110 %
b110 (
b110 )
1"
#1160
0"
#1170
b100 &
b100 '
b100 *
b101 !
b101 $
b101 %
b101 (
b101 )
1"
#1180
0"
#1190
b11 &
b11 '
b11 *
b100 !
b100 $
b100 %
b100 (
b100 )
1"
#1200
0"
#1210
b10 &
b10 '
b10 *
b11 !
b11 $
b11 %
b11 (
b11 )
1"
#1220
0"
#1230
b1 &
b1 '
b1 *
b10 !
b10 $
b10 %
b10 (
b10 )
1"
#1240
0"
#1250
b0 &
b0 '
b0 *
b1 !
b1 $
b1 %
b1 (
b1 )
1"
#1260
0"
#1270
b1111 &
b1111 '
b1111 *
b0 !
b0 $
b0 %
b0 (
b0 )
1"
#1280
0"
#1290
b1110 &
b1110 '
b1110 *
b1111 !
b1111 $
b1111 %
b1111 (
b1111 )
1"
#1300
0"
#1310
b1101 &
b1101 '
b1101 *
b1110 !
b1110 $
b1110 %
b1110 (
b1110 )
1"
#1320
0"
#1330
b1100 &
b1100 '
b1100 *
b1101 !
b1101 $
b1101 %
b1101 (
b1101 )
1"
#1340
0"
#1350
b1011 &
b1011 '
b1011 *
b1100 !
b1100 $
b1100 %
b1100 (
b1100 )
1"
#1360
0"
#1370
b1010 &
b1010 '
b1010 *
b1011 !
b1011 $
b1011 %
b1011 (
b1011 )
1"
#1380
0"
#1390
b1001 &
b1001 '
b1001 *
b1010 !
b1010 $
b1010 %
b1010 (
b1010 )
1"
#1400
0"
#1410
b1000 &
b1000 '
b1000 *
b1001 !
b1001 $
b1001 %
b1001 (
b1001 )
1"
#1420
0"
#1430
b111 &
b111 '
b111 *
b1000 !
b1000 $
b1000 %
b1000 (
b1000 )
1"
#1440
0"
#1450
b110 &
b110 '
b110 *
b111 !
b111 $
b111 %
b111 (
b111 )
1"
#1460
0"
#1470
b101 &
b101 '
b101 *
b110 !
b110 $
b110 %
b110 (
b110 )
1"
#1480
0"
#1490
b100 &
b100 '
b100 *
b101 !
b101 $
b101 %
b101 (
b101 )
1"
#1500
0"
#1510
b11 &
b11 '
b11 *
b100 !
b100 $
b100 %
b100 (
b100 )
1"
#1520
0"
#1530
b10 &
b10 '
b10 *
b11 !
b11 $
b11 %
b11 (
b11 )
1"
#1540
0"
#1550
b1 &
b1 '
b1 *
b10 !
b10 $
b10 %
b10 (
b10 )
1"
#1560
0"
#1570
b0 &
b0 '
b0 *
b1 !
b1 $
b1 %
b1 (
b1 )
1"
#1580
0"
#1590
b1111 &
b1111 '
b1111 *
b0 !
b0 $
b0 %
b0 (
b0 )
1"
#1600
0"
#1610
b1110 &
b1110 '
b1110 *
b1111 !
b1111 $
b1111 %
b1111 (
b1111 )
1"
#1620
0"
#1630
b1101 &
b1101 '
b1101 *
b1110 !
b1110 $
b1110 %
b1110 (
b1110 )
1"
#1640
0"
#1650
b1100 &
b1100 '
b1100 *
b1101 !
b1101 $
b1101 %
b1101 (
b1101 )
1"
#1660
0"
#1670
b1011 &
b1011 '
b1011 *
b1100 !
b1100 $
b1100 %
b1100 (
b1100 )
1"
#1680
0"
#1690
b1010 &
b1010 '
b1010 *
b1011 !
b1011 $
b1011 %
b1011 (
b1011 )
1"
#1700
0"
#1710
b1001 &
b1001 '
b1001 *
b1010 !
b1010 $
b1010 %
b1010 (
b1010 )
1"
#1720
0"
#1730
b1000 &
b1000 '
b1000 *
b1001 !
b1001 $
b1001 %
b1001 (
b1001 )
1"
#1740
0"
#1750
b111 &
b111 '
b111 *
b1000 !
b1000 $
b1000 %
b1000 (
b1000 )
1"
#1760
0"
#1770
b110 &
b110 '
b110 *
b111 !
b111 $
b111 %
b111 (
b111 )
1"
#1780
0"
#1790
b101 &
b101 '
b101 *
b110 !
b110 $
b110 %
b110 (
b110 )
1"
#1800
0"
#1810
b100 &
b100 '
b100 *
b101 !
b101 $
b101 %
b101 (
b101 )
1"
#1820
0"
#1830
b11 &
b11 '
b11 *
b100 !
b100 $
b100 %
b100 (
b100 )
1"
#1840
0"
#1850
b10 &
b10 '
b10 *
b11 !
b11 $
b11 %
b11 (
b11 )
1"
#1860
0"
#1870
b1 &
b1 '
b1 *
b10 !
b10 $
b10 %
b10 (
b10 )
1"
#1880
0"
#1890
b0 &
b0 '
b0 *
b1 !
b1 $
b1 %
b1 (
b1 )
1"
#1900
0"
#1910
b1111 &
b1111 '
b1111 *
b0 !
b0 $
b0 %
b0 (
b0 )
1"
#1920
0"
#1930
b1110 &
b1110 '
b1110 *
b1111 !
b1111 $
b1111 %
b1111 (
b1111 )
1"
#1940
0"
#1950
b1101 &
b1101 '
b1101 *
b1110 !
b1110 $
b1110 %
b1110 (
b1110 )
1"
#1960
0"
#1970
b1100 &
b1100 '
b1100 *
b1101 !
b1101 $
b1101 %
b1101 (
b1101 )
1"
#1980
0"
#1990
b1011 &
b1011 '
b1011 *
b1100 !
b1100 $
b1100 %
b1100 (
b1100 )
1"
#2000
0"
#2010
b1010 &
b1010 '
b1010 *
b1011 !
b1011 $
b1011 %
b1011 (
b1011 )
1"
#2020
0"
#2030
b1001 &
b1001 '
b1001 *
b1010 !
b1010 $
b1010 %
b1010 (
b1010 )
1"
#2040
0"
#2050
b1000 &
b1000 '
b1000 *
b1001 !
b1001 $
b1001 %
b1001 (
b1001 )
1"
#2060
0"
#2070
b111 &
b111 '
b111 *
b1000 !
b1000 $
b1000 %
b1000 (
b1000 )
1"
#2080
0"
#2090
b110 &
b110 '
b110 *
b111 !
b111 $
b111 %
b111 (
b111 )
1"
#2100
0"
#2110
b101 &
b101 '
b101 *
b110 !
b110 $
b110 %
b110 (
b110 )
1"
#2120
0"
#2130
b100 &
b100 '
b100 *
b101 !
b101 $
b101 %
b101 (
b101 )
1"
#2140
0"
#2150
b11 &
b11 '
b11 *
b100 !
b100 $
b100 %
b100 (
b100 )
1"
#2160
0"
#2170
b10 &
b10 '
b10 *
b11 !
b11 $
b11 %
b11 (
b11 )
1"
#2180
0"
#2190
b1 &
b1 '
b1 *
b10 !
b10 $
b10 %
b10 (
b10 )
1"
#2200
0"
#2210
b0 &
b0 '
b0 *
b1 !
b1 $
b1 %
b1 (
b1 )
1"
#2220
0"
#2230
b1111 &
b1111 '
b1111 *
b0 !
b0 $
b0 %
b0 (
b0 )
1"
#2240
0"
#2250
b1110 &
b1110 '
b1110 *
b1111 !
b1111 $
b1111 %
b1111 (
b1111 )
1"
#2260
0"
#2270
b1101 &
b1101 '
b1101 *
b1110 !
b1110 $
b1110 %
b1110 (
b1110 )
1"
#2280
0"
#2290
b1100 &
b1100 '
b1100 *
b1101 !
b1101 $
b1101 %
b1101 (
b1101 )
1"
#2300
0"
#2310
b1011 &
b1011 '
b1011 *
b1100 !
b1100 $
b1100 %
b1100 (
b1100 )
1"
#2320
0"
#2330
b1010 &
b1010 '
b1010 *
b1011 !
b1011 $
b1011 %
b1011 (
b1011 )
1"
#2340
0"
#2350
b1001 &
b1001 '
b1001 *
b1010 !
b1010 $
b1010 %
b1010 (
b1010 )
1"
#2360
0"
#2370
b1000 &
b1000 '
b1000 *
b1001 !
b1001 $
b1001 %
b1001 (
b1001 )
1"
#2380
0"
#2390
b111 &
b111 '
b111 *
b1000 !
b1000 $
b1000 %
b1000 (
b1000 )
1"
#2400
0"
#2410
b110 &
b110 '
b110 *
b111 !
b111 $
b111 %
b111 (
b111 )
1"
#2420
0"
#2430
b101 &
b101 '
b101 *
b110 !
b110 $
b110 %
b110 (
b110 )
1"
#2440
0"
#2450
b100 &
b100 '
b100 *
b101 !
b101 $
b101 %
b101 (
b101 )
1"
#2460
0"
#2470
b11 &
b11 '
b11 *
b100 !
b100 $
b100 %
b100 (
b100 )
1"
#2480
0"
#2490
b10 &
b10 '
b10 *
b11 !
b11 $
b11 %
b11 (
b11 )
1"
#2500
0"
#2510
b1 &
b1 '
b1 *
b10 !
b10 $
b10 %
b10 (
b10 )
1"
#2520
0"
#2530
b0 &
b0 '
b0 *
b1 !
b1 $
b1 %
b1 (
b1 )
1"
#2540
0"
#2550
b1111 &
b1111 '
b1111 *
b0 !
b0 $
b0 %
b0 (
b0 )
1"
#2560
0"
#2570
b1110 &
b1110 '
b1110 *
b1111 !
b1111 $
b1111 %
b1111 (
b1111 )
1"
#2580
0"
#2590
b1101 &
b1101 '
b1101 *
b1110 !
b1110 $
b1110 %
b1110 (
b1110 )
1"
#2600
0"
#2610
b1100 &
b1100 '
b1100 *
b1101 !
b1101 $
b1101 %
b1101 (
b1101 )
1"
#2620
0"
#2630
b1011 &
b1011 '
b1011 *
b1100 !
b1100 $
b1100 %
b1100 (
b1100 )
1"
#2640
0"
#2650
b1010 &
b1010 '
b1010 *
b1011 !
b1011 $
b1011 %
b1011 (
b1011 )
1"
#2660
0"
#2670
b1001 &
b1001 '
b1001 *
b1010 !
b1010 $
b1010 %
b1010 (
b1010 )
1"
#2680
0"
#2690
b1000 &
b1000 '
b1000 *
b1001 !
b1001 $
b1001 %
b1001 (
b1001 )
1"
#2700
0"
#2710
b111 &
b111 '
b111 *
b1000 !
b1000 $
b1000 %
b1000 (
b1000 )
1"
#2720
0"
#2730
b110 &
b110 '
b110 *
b111 !
b111 $
b111 %
b111 (
b111 )
1"
#2740
0"
#2750
b101 &
b101 '
b101 *
b110 !
b110 $
b110 %
b110 (
b110 )
1"
#2760
0"
#2770
b100 &
b100 '
b100 *
b101 !
b101 $
b101 %
b101 (
b101 )
1"
#2780
0"
#2790
b11 &
b11 '
b11 *
b100 !
b100 $
b100 %
b100 (
b100 )
1"
#2800
0"
#2810
b10 &
b10 '
b10 *
b11 !
b11 $
b11 %
b11 (
b11 )
1"
#2820
0"
#2830
b1 &
b1 '
b1 *
b10 !
b10 $
b10 %
b10 (
b10 )
1"
#2840
0"
#2850
b0 &
b0 '
b0 *
b1 !
b1 $
b1 %
b1 (
b1 )
1"
#2860
0"
#2870
b1111 &
b1111 '
b1111 *
b0 !
b0 $
b0 %
b0 (
b0 )
1"
#2880
0"
#2890
b1110 &
b1110 '
b1110 *
b1111 !
b1111 $
b1111 %
b1111 (
b1111 )
1"
#2900
0"
#2910
b1101 &
b1101 '
b1101 *
b1110 !
b1110 $
b1110 %
b1110 (
b1110 )
1"
#2920
0"
#2930
b1100 &
b1100 '
b1100 *
b1101 !
b1101 $
b1101 %
b1101 (
b1101 )
1"
#2940
0"
#2950
b1011 &
b1011 '
b1011 *
b1100 !
b1100 $
b1100 %
b1100 (
b1100 )
1"
#2960
0"
#2970
b1010 &
b1010 '
b1010 *
b1011 !
b1011 $
b1011 %
b1011 (
b1011 )
1"
#2980
0"
#2990
b1001 &
b1001 '
b1001 *
b1010 !
b1010 $
b1010 %
b1010 (
b1010 )
1"
#3000
0"
#3010
b1000 &
b1000 '
b1000 *
b1001 !
b1001 $
b1001 %
b1001 (
b1001 )
1"
#3020
0"
#3030
b111 &
b111 '
b111 *
b1000 !
b1000 $
b1000 %
b1000 (
b1000 )
1"
#3040
0"
#3050
b110 &
b110 '
b110 *
b111 !
b111 $
b111 %
b111 (
b111 )
1"
#3060
0"
#3070
b101 &
b101 '
b101 *
b110 !
b110 $
b110 %
b110 (
b110 )
1"
#3080
0"
#3090
b100 &
b100 '
b100 *
b101 !
b101 $
b101 %
b101 (
b101 )
1"
#3100
0"
#3110
b11 &
b11 '
b11 *
b100 !
b100 $
b100 %
b100 (
b100 )
1"
#3120
0"
#3130
b10 &
b10 '
b10 *
b11 !
b11 $
b11 %
b11 (
b11 )
1"
#3140
0"
#3150
b1 &
b1 '
b1 *
b10 !
b10 $
b10 %
b10 (
b10 )
1"
#3160
0"
#3170
b0 &
b0 '
b0 *
b1 !
b1 $
b1 %
b1 (
b1 )
1"
#3180
0"
#3190
b1111 &
b1111 '
b1111 *
b0 !
b0 $
b0 %
b0 (
b0 )
1"
#3200
0"
#3210
b1110 &
b1110 '
b1110 *
b1111 !
b1111 $
b1111 %
b1111 (
b1111 )
1"
#3220
0"
#3230
b1101 &
b1101 '
b1101 *
b1110 !
b1110 $
b1110 %
b1110 (
b1110 )
1"
#3240
0"
#3250
b1100 &
b1100 '
b1100 *
b1101 !
b1101 $
b1101 %
b1101 (
b1101 )
1"
#3260
0"
#3270
b1011 &
b1011 '
b1011 *
b1100 !
b1100 $
b1100 %
b1100 (
b1100 )
1"
#3280
0"
#3290
b1010 &
b1010 '
b1010 *
b1011 !
b1011 $
b1011 %
b1011 (
b1011 )
1"
#3300
0"
#3310
b1001 &
b1001 '
b1001 *
b1010 !
b1010 $
b1010 %
b1010 (
b1010 )
1"
#3320
0"
#3330
b1000 &
b1000 '
b1000 *
b1001 !
b1001 $
b1001 %
b1001 (
b1001 )
1"
#3340
0"
#3350
b111 &
b111 '
b111 *
b1000 !
b1000 $
b1000 %
b1000 (
b1000 )
1"
#3360
0"
#3370
b110 &
b110 '
b110 *
b111 !
b111 $
b111 %
b111 (
b111 )
1"
#3380
0"
#3390
b101 &
b101 '
b101 *
b110 !
b110 $
b110 %
b110 (
b110 )
1"
#3400
0"
#3410
b100 &
b100 '
b100 *
b101 !
b101 $
b101 %
b101 (
b101 )
1"
#3420
0"
#3430
b11 &
b11 '
b11 *
b100 !
b100 $
b100 %
b100 (
b100 )
1"
#3440
0"
#3450
b10 &
b10 '
b10 *
b11 !
b11 $
b11 %
b11 (
b11 )
1"
#3460
0"
#3470
b1 &
b1 '
b1 *
b10 !
b10 $
b10 %
b10 (
b10 )
1"
#3480
0"
#3490
b0 &
b0 '
b0 *
b1 !
b1 $
b1 %
b1 (
b1 )
1"
#3500
0"
#3510
b1111 &
b1111 '
b1111 *
b0 !
b0 $
b0 %
b0 (
b0 )
1"
#3520
0"
#3530
b1110 &
b1110 '
b1110 *
b1111 !
b1111 $
b1111 %
b1111 (
b1111 )
1"
#3540
0"
#3550
b1101 &
b1101 '
b1101 *
b1110 !
b1110 $
b1110 %
b1110 (
b1110 )
1"
#3560
0"
#3570
b1100 &
b1100 '
b1100 *
b1101 !
b1101 $
b1101 %
b1101 (
b1101 )
1"
#3580
0"
#3590
b1011 &
b1011 '
b1011 *
b1100 !
b1100 $
b1100 %
b1100 (
b1100 )
1"
#3600
0"
#3610
b1010 &
b1010 '
b1010 *
b1011 !
b1011 $
b1011 %
b1011 (
b1011 )
1"
#3620
0"
#3630
b1001 &
b1001 '
b1001 *
b1010 !
b1010 $
b1010 %
b1010 (
b1010 )
1"
#3640
0"
#3650
b1000 &
b1000 '
b1000 *
b1001 !
b1001 $
b1001 %
b1001 (
b1001 )
1"
#3660
0"
#3670
b111 &
b111 '
b111 *
b1000 !
b1000 $
b1000 %
b1000 (
b1000 )
1"
#3680
0"
#3690
b110 &
b110 '
b110 *
b111 !
b111 $
b111 %
b111 (
b111 )
1"
#3700
0"
#3710
b101 &
b101 '
b101 *
b110 !
b110 $
b110 %
b110 (
b110 )
1"
#3720
0"
#3730
b100 &
b100 '
b100 *
b101 !
b101 $
b101 %
b101 (
b101 )
1"
#3740
0"
#3750
b11 &
b11 '
b11 *
b100 !
b100 $
b100 %
b100 (
b100 )
1"
#3760
0"
#3770
b10 &
b10 '
b10 *
b11 !
b11 $
b11 %
b11 (
b11 )
1"
#3780
0"
#3790
b1 &
b1 '
b1 *
b10 !
b10 $
b10 %
b10 (
b10 )
1"
#3800
0"
#3810
b0 &
b0 '
b0 *
b1 !
b1 $
b1 %
b1 (
b1 )
1"
#3820
0"
#3830
b1111 &
b1111 '
b1111 *
b0 !
b0 $
b0 %
b0 (
b0 )
1"
#3840
0"
#3850
b1110 &
b1110 '
b1110 *
b1111 !
b1111 $
b1111 %
b1111 (
b1111 )
1"
#3860
0"
#3870
b1101 &
b1101 '
b1101 *
b1110 !
b1110 $
b1110 %
b1110 (
b1110 )
1"
#3880
0"
#3890
b1100 &
b1100 '
b1100 *
b1101 !
b1101 $
b1101 %
b1101 (
b1101 )
1"
#3900
0"
#3910
b1011 &
b1011 '
b1011 *
b1100 !
b1100 $
b1100 %
b1100 (
b1100 )
1"
#3920
0"
#3930
b1010 &
b1010 '
b1010 *
b1011 !
b1011 $
b1011 %
b1011 (
b1011 )
1"
#3940
0"
#3950
b1001 &
b1001 '
b1001 *
b1010 !
b1010 $
b1010 %
b1010 (
b1010 )
1"
#3960
0"
#3970
b1000 &
b1000 '
b1000 *
b1001 !
b1001 $
b1001 %
b1001 (
b1001 )
1"
#3980
0"
#3990
b111 &
b111 '
b111 *
b1000 !
b1000 $
b1000 %
b1000 (
b1000 )
1"
#4000
0"
#4010
b110 &
b110 '
b110 *
b111 !
b111 $
b111 %
b111 (
b111 )
1"
#4020
0"
#4030
b101 &
b101 '
b101 *
b110 !
b110 $
b110 %
b110 (
b110 )
1"
#4040
0"
#4050
b100 &
b100 '
b100 *
b101 !
b101 $
b101 %
b101 (
b101 )
1"
#4060
0"
#4070
b11 &
b11 '
b11 *
b100 !
b100 $
b100 %
b100 (
b100 )
1"
#4080
0"
#4090
b10 &
b10 '
b10 *
b11 !
b11 $
b11 %
b11 (
b11 )
1"
#4100
0"
#4110
b1 &
b1 '
b1 *
b10 !
b10 $
b10 %
b10 (
b10 )
1"
#4120
0"
#4130
b0 &
b0 '
b0 *
b1 !
b1 $
b1 %
b1 (
b1 )
1"
#4140
0"
#4150
b1111 &
b1111 '
b1111 *
b0 !
b0 $
b0 %
b0 (
b0 )
1"
#4160
0"
#4170
b1110 &
b1110 '
b1110 *
b1111 !
b1111 $
b1111 %
b1111 (
b1111 )
1"
#4180
0"
#4190
b1101 &
b1101 '
b1101 *
b1110 !
b1110 $
b1110 %
b1110 (
b1110 )
1"
#4200
0"
#4210
b1100 &
b1100 '
b1100 *
b1101 !
b1101 $
b1101 %
b1101 (
b1101 )
1"
#4220
0"
#4230
b1011 &
b1011 '
b1011 *
b1100 !
b1100 $
b1100 %
b1100 (
b1100 )
1"
#4240
0"
#4250
b1010 &
b1010 '
b1010 *
b1011 !
b1011 $
b1011 %
b1011 (
b1011 )
1"
#4260
0"
#4270
b1001 &
b1001 '
b1001 *
b1010 !
b1010 $
b1010 %
b1010 (
b1010 )
1"
#4280
0"
#4290
b1000 &
b1000 '
b1000 *
b1001 !
b1001 $
b1001 %
b1001 (
b1001 )
1"
#4300
0"
#4310
b111 &
b111 '
b111 *
b1000 !
b1000 $
b1000 %
b1000 (
b1000 )
1"
#4320
0"
#4330
b110 &
b110 '
b110 *
b111 !
b111 $
b111 %
b111 (
b111 )
1"
#4340
0"
#4350
b101 &
b101 '
b101 *
b110 !
b110 $
b110 %
b110 (
b110 )
1"
#4360
0"
#4370
b100 &
b100 '
b100 *
b101 !
b101 $
b101 %
b101 (
b101 )
1"
#4380
0"
#4390
b11 &
b11 '
b11 *
b100 !
b100 $
b100 %
b100 (
b100 )
1"
#4400
0"
#4410
b10 &
b10 '
b10 *
b11 !
b11 $
b11 %
b11 (
b11 )
1"
#4420
0"
#4430
b1 &
b1 '
b1 *
b10 !
b10 $
b10 %
b10 (
b10 )
1"
#4440
0"
#4450
b0 &
b0 '
b0 *
b1 !
b1 $
b1 %
b1 (
b1 )
1"
#4460
0"
#4470
b1111 &
b1111 '
b1111 *
b0 !
b0 $
b0 %
b0 (
b0 )
1"
#4480
0"
#4490
b1110 &
b1110 '
b1110 *
b1111 !
b1111 $
b1111 %
b1111 (
b1111 )
1"
#4500
0"
#4510
b1101 &
b1101 '
b1101 *
b1110 !
b1110 $
b1110 %
b1110 (
b1110 )
1"
#4520
0"
#4530
b1100 &
b1100 '
b1100 *
b1101 !
b1101 $
b1101 %
b1101 (
b1101 )
1"
#4540
0"
#4550
b1011 &
b1011 '
b1011 *
b1100 !
b1100 $
b1100 %
b1100 (
b1100 )
1"
#4560
0"
#4570
b1010 &
b1010 '
b1010 *
b1011 !
b1011 $
b1011 %
b1011 (
b1011 )
1"
#4580
0"
#4590
b1001 &
b1001 '
b1001 *
b1010 !
b1010 $
b1010 %
b1010 (
b1010 )
1"
#4600
0"
#4610
b1000 &
b1000 '
b1000 *
b1001 !
b1001 $
b1001 %
b1001 (
b1001 )
1"
#4620
0"
#4630
b111 &
b111 '
b111 *
b1000 !
b1000 $
b1000 %
b1000 (
b1000 )
1"
#4640
0"
#4650
b110 &
b110 '
b110 *
b111 !
b111 $
b111 %
b111 (
b111 )
1"
#4660
0"
#4670
b101 &
b101 '
b101 *
b110 !
b110 $
b110 %
b110 (
b110 )
1"
#4680
0"
#4690
b100 &
b100 '
b100 *
b101 !
b101 $
b101 %
b101 (
b101 )
1"
#4700
0"
#4710
b11 &
b11 '
b11 *
b100 !
b100 $
b100 %
b100 (
b100 )
1"
#4720
0"
#4730
b10 &
b10 '
b10 *
b11 !
b11 $
b11 %
b11 (
b11 )
1"
#4740
0"
#4750
b1 &
b1 '
b1 *
b10 !
b10 $
b10 %
b10 (
b10 )
1"
#4760
0"
#4770
b0 &
b0 '
b0 *
b1 !
b1 $
b1 %
b1 (
b1 )
1"
#4780
0"
#4790
b1111 &
b1111 '
b1111 *
b0 !
b0 $
b0 %
b0 (
b0 )
1"
#4800
0"
#4810
b1110 &
b1110 '
b1110 *
b1111 !
b1111 $
b1111 %
b1111 (
b1111 )
1"
#4820
0"
#4830
b1101 &
b1101 '
b1101 *
b1110 !
b1110 $
b1110 %
b1110 (
b1110 )
1"
#4840
0"
