Computer_Architecture/HDL(Combinational)/Decoder(3to8)/Using case/decoder3to8.v
module decoder3to8
(
    input E,
    input [2:0] A,
    output reg [7:0] Y
);

always @*
begin
    case({E,A})
        4'b1000 : Y = 8'b00000001;
        4'b1001 : Y = 8'b00000010;
        4'b1010 : Y = 8'b00000100;
        4'b1011 : Y = 8'b00001000;
        4'b1100 : Y = 8'b00010000;
        4'b1101 : Y = 8'b00100000;
        4'b1110 : Y = 8'b01000000;
        4'b1111 : Y = 8'b10000000;
        default : Y = 8'b00000000;
    endcase
end    

endmodule

Computer_Architecture/HDL(Combinational)/Decoder(3to8)/Using case/decoder3to8_tb.v
`timescale 1ns/1ps

module decoder3to8_tb;

reg [2:0] A;
reg E;
wire [7:0] Y;

decoder3to8 uut
(
   .A(A),
   .E(E),
   .Y(Y)
);

initial begin
    $dumpfile("decoder3to8_tb.vcd");
    $dumpvars(0,decoder3to8_tb);
    
    E=0;
    A=3'b000;
    
    #20 E=1;
    #20 A=3'b000;
    #20 A=3'b001;
    #20 A=3'b010;
    #20 A=3'b011;
    #20 A=3'b100;
    #20 A=3'b101;
    #20 A=3'b110;
    #20 A=3'b111;
    #20;
    $finish;
end

initial begin
    $monitor("E=%b|A2=%b|A1=%b|A0=%b|Y7=%b|Y6=%b|Y5=%b|Y4=%b|Y3=%b|Y2=%b|Y1=%b|Y0=%b",E,A[2],A[1],A[0],Y[7],Y[6],Y[5],Y[4],Y[3],Y[2],Y[1],Y[0]);
end
endmodule

Computer_Architecture/HDL(Combinational)/Decoder(3to8)/Using case/decoder3to8_tb.vcd
$date
	Mon May 13 23:05:04 2024
$end
$version
	Icarus Verilog
$end
$timescale
	1ps
$end
$scope module decoder3to8_tb $end
$var wire 8 ! Y [7:0] $end
$var reg 3 " A [2:0] $end
$var reg 1 # E $end
$scope module uut $end
$var wire 3 $ A [2:0] $end
$var wire 1 # E $end
$var reg 8 % Y [7:0] $end
$upscope $end
$upscope $end
$enddefinitions $end
$comment Show the parameter values. $end
$dumpall
$end
#0
$dumpvars
b0 %
b0 $
0#
b0 "
b0 !
$end
#20000
b1 !
b1 %
1#
#60000
b10 !
b10 %
b1 "
b1 $
#80000
b100 !
b100 %
b10 "
b10 $
#100000
b1000 !
b1000 %
b11 "
b11 $
#120000
b10000 !
b10000 %
b100 "
b100 $
#140000
b100000 !
b100000 %
b101 "
b101 $
#160000
b1000000 !
b1000000 %
b110 "
b110 $
#180000
b10000000 !
b10000000 %
b111 "
b111 $
