Computer_Architecture/HDL2/RSET/RF1bit.v
module RF1bit (
    input wire clk,
    input wire reset,
    input wire Din,
    input wire Sel,  
    output wire Dout
);
    reg DFF;
    
    always @(posedge clk , posedge reset) 
    begin
        if (reset) 
            DFF <= 1'b0;       
        else if (Sel) 
            DFF <= Din;               
    end

    assign Dout = DFF;

endmodule

Computer_Architecture/HDL2/RSET/RF4bit.v
module RF4bit (
    input wire clk,
    input wire reset,
    input wire [3:0] Din,
    input wire Sel,  
    output wire [3:0] Dout
);

    RF1bit cir1stbit (.clk(clk), .reset(reset), .Din(Din[0]), .Sel(Sel), .Dout(Dout[0]));
    RF1bit cir2ndbit (.clk(clk), .reset(reset), .Din(Din[1]), .Sel(Sel), .Dout(Dout[1]));
    RF1bit cir3rdbit (.clk(clk), .reset(reset), .Din(Din[2]), .Sel(Sel), .Dout(Dout[2]));
    RF1bit cir4thbit (.clk(clk), .reset(reset), .Din(Din[3]), .Sel(Sel), .Dout(Dout[3]));
    
endmodule

Computer_Architecture/HDL2/RSET/RFSet.v
module RFSet (
    input wire clk,
    input wire reset,
    input wire [1:0] RA,
    input wire [1:0] RB,
    input wire RE,  
    input wire [1:0] WR,  
    input wire [3:0] WRD,
    output reg [3:0] A,
    output reg [3:0] B
);

    wire [3:0] R00, R01, R10, R11;
    reg [3:0] WR_SEL;

    RF4bit Reg00 (.clk(clk), .reset(reset), .Din(WRD), .Sel(WR_SEL[0]), .Dout(R00));
    RF4bit Reg01 (.clk(clk), .reset(reset), .Din(WRD), .Sel(WR_SEL[1]), .Dout(R01));
    RF4bit Reg10 (.clk(clk), .reset(reset), .Din(WRD), .Sel(WR_SEL[2]), .Dout(R10));
    RF4bit Reg11 (.clk(clk), .reset(reset), .Din(WRD), .Sel(WR_SEL[3]), .Dout(R11));
    
    always @(*) 
       begin
            case ({RE, WR})
                3'b100: WR_SEL = 4'b0001;  
                3'b101: WR_SEL = 4'b0010;  
                3'b110: WR_SEL = 4'b0100;  
                3'b111: WR_SEL = 4'b1000;  
                default: WR_SEL = 4'b0000; 
            endcase
        end 

    always @(*) 
        begin
            case (RA)
                2'b00: A = R00;
                2'b01: A = R01;
                2'b10: A = R10;
                2'b11: A = R11;
                default: A = 4'b0000;
            endcase
        end

    always @(*) 
        begin
            case (RB)
                2'b00: B = R00;
                2'b01: B = R01;
                2'b10: B = R10;
                2'b11: B = R11;
                default: B = 4'b0000;
            endcase
        end

endmodule

Computer_Architecture/HDL2/RSET/RFSet_tb.v
`timescale 1ns/1ns

module RFSet_tb;
    reg clk;
    reg reset;
    reg [1:0] RA;
    reg [1:0] RB;
    reg RE;
    reg [1:0] WR;
    reg [3:0] WRD;
    wire [3:0] A;
    wire [3:0] B;

    RFSet uut (
        .clk(clk),
        .reset(reset),
        .RA(RA),
        .RB(RB),
        .RE(RE),
        .WR(WR),
        .WRD(WRD),
        .A(A),
        .B(B)
    );

    always 
    begin
        clk = ~clk; 
        #5;
    end 

    initial begin
        $dumpfile("test3.vcd");
        $dumpvars(0, RFSet_tb);

        clk = 0;
        reset = 1;  
        RA = 2'b00;
        RB = 2'b00;
        RE = 0;
        WR = 2'b00;
        WRD = 4'b0000;
        #10;

        reset = 0;  
        #10;

        RE = 1; 
        
        WR = 2'b00; WRD = 4'b1101; RA = 2'b00; RB = 2'b00; 
        #10;

        WR = 2'b01; WRD = 4'b0011; RA = 2'b01; RB = 2'b01; 
        #10;

        WR = 2'b10; WRD = 4'b1010; RA = 2'b10; RB = 2'b10; 
        #10;

        WR = 2'b11; WRD = 4'b0111; RA = 2'b11; RB = 2'b11; 
        #10;

        RE = 0; 

        WR = 2'b00; WRD = 4'b1111; RA = 2'b00; RB = 2'b00; 
        #10;

        $finish;
    end

    initial begin
        $monitor("Time = %0t | clk = %b | reset = %b | RA = %b | RB = %b | WR = %b | WRD = %b | RE = %b | A = %b | B = %b", 
                 $time, clk, reset, RA, RB, WR, WRD, RE, A, B);
    end

endmodule

Computer_Architecture/HDL2/RSET/test3.vcd
$date
	Sat Sep 21 00:08:33 2024
$end
$version
	Icarus Verilog
$end
$timescale
	1ns
$end
$scope module RFSet_tb $end
$var wire 4 ! B [3:0] $end
$var wire 4 " A [3:0] $end
$var reg 2 # RA [1:0] $end
$var reg 2 $ RB [1:0] $end
$var reg 1 % RE $end
$var reg 2 & WR [1:0] $end
$var reg 4 ' WRD [3:0] $end
$var reg 1 ( clk $end
$var reg 1 ) reset $end
$scope module uut $end
$var wire 2 * RA [1:0] $end
$var wire 2 + RB [1:0] $end
$var wire 1 % RE $end
$var wire 2 , WR [1:0] $end
$var wire 4 - WRD [3:0] $end
$var wire 1 ( clk $end
$var wire 1 ) reset $end
$var wire 4 . R11 [3:0] $end
$var wire 4 / R10 [3:0] $end
$var wire 4 0 R01 [3:0] $end
$var wire 4 1 R00 [3:0] $end
$var reg 4 2 A [3:0] $end
$var reg 4 3 B [3:0] $end
$var reg 4 4 WR_SEL [3:0] $end
$scope module Reg00 $end
$var wire 4 5 Din [3:0] $end
$var wire 1 6 Sel $end
$var wire 1 ( clk $end
$var wire 1 ) reset $end
$var wire 4 7 Dout [3:0] $end
$scope module cir1stbit $end
$var wire 1 8 Din $end
$var wire 1 9 Dout $end
$var wire 1 6 Sel $end
$var wire 1 ( clk $end
$var wire 1 ) reset $end
$var reg 1 9 DFF $end
$upscope $end
$scope module cir2ndbit $end
$var wire 1 : Din $end
$var wire 1 ; Dout $end
$var wire 1 6 Sel $end
$var wire 1 ( clk $end
$var wire 1 ) reset $end
$var reg 1 ; DFF $end
$upscope $end
$scope module cir3rdbit $end
$var wire 1 < Din $end
$var wire 1 = Dout $end
$var wire 1 6 Sel $end
$var wire 1 ( clk $end
$var wire 1 ) reset $end
$var reg 1 = DFF $end
$upscope $end
$scope module cir4thbit $end
$var wire 1 > Din $end
$var wire 1 ? Dout $end
$var wire 1 6 Sel $end
$var wire 1 ( clk $end
$var wire 1 ) reset $end
$var reg 1 ? DFF $end
$upscope $end
$upscope $end
$scope module Reg01 $end
$var wire 4 @ Din [3:0] $end
$var wire 1 A Sel $end
$var wire 1 ( clk $end
$var wire 1 ) reset $end
$var wire 4 B Dout [3:0] $end
$scope module cir1stbit $end
$var wire 1 C Din $end
$var wire 1 D Dout $end
$var wire 1 A Sel $end
$var wire 1 ( clk $end
$var wire 1 ) reset $end
$var reg 1 D DFF $end
$upscope $end
$scope module cir2ndbit $end
$var wire 1 E Din $end
$var wire 1 F Dout $end
$var wire 1 A Sel $end
$var wire 1 ( clk $end
$var wire 1 ) reset $end
$var reg 1 F DFF $end
$upscope $end
$scope module cir3rdbit $end
$var wire 1 G Din $end
$var wire 1 H Dout $end
$var wire 1 A Sel $end
$var wire 1 ( clk $end
$var wire 1 ) reset $end
$var reg 1 H DFF $end
$upscope $end
$scope module cir4thbit $end
$var wire 1 I Din $end
$var wire 1 J Dout $end
$var wire 1 A Sel $end
$var wire 1 ( clk $end
$var wire 1 ) reset $end
$var reg 1 J DFF $end
$upscope $end
$upscope $end
$scope module Reg10 $end
$var wire 4 K Din [3:0] $end
$var wire 1 L Sel $end
$var wire 1 ( clk $end
$var wire 1 ) reset $end
$var wire 4 M Dout [3:0] $end
$scope module cir1stbit $end
$var wire 1 N Din $end
$var wire 1 O Dout $end
$var wire 1 L Sel $end
$var wire 1 ( clk $end
$var wire 1 ) reset $end
$var reg 1 O DFF $end
$upscope $end
$scope module cir2ndbit $end
$var wire 1 P Din $end
$var wire 1 Q Dout $end
$var wire 1 L Sel $end
$var wire 1 ( clk $end
$var wire 1 ) reset $end
$var reg 1 Q DFF $end
$upscope $end
$scope module cir3rdbit $end
$var wire 1 R Din $end
$var wire 1 S Dout $end
$var wire 1 L Sel $end
$var wire 1 ( clk $end
$var wire 1 ) reset $end
$var reg 1 S DFF $end
$upscope $end
$scope module cir4thbit $end
$var wire 1 T Din $end
$var wire 1 U Dout $end
$var wire 1 L Sel $end
$var wire 1 ( clk $end
$var wire 1 ) reset $end
$var reg 1 U DFF $end
$upscope $end
$upscope $end
$scope module Reg11 $end
$var wire 4 V Din [3:0] $end
$var wire 1 W Sel $end
$var wire 1 ( clk $end
$var wire 1 ) reset $end
$var wire 4 X Dout [3:0] $end
$scope module cir1stbit $end
$var wire 1 Y Din $end
$var wire 1 Z Dout $end
$var wire 1 W Sel $end
$var wire 1 ( clk $end
$var wire 1 ) reset $end
$var reg 1 Z DFF $end
$upscope $end
$scope module cir2ndbit $end
$var wire 1 [ Din $end
$var wire 1 \ Dout $end
$var wire 1 W Sel $end
$var wire 1 ( clk $end
$var wire 1 ) reset $end
$var reg 1 \ DFF $end
$upscope $end
$scope module cir3rdbit $end
$var wire 1 ] Din $end
$var wire 1 ^ Dout $end
$var wire 1 W Sel $end
$var wire 1 ( clk $end
$var wire 1 ) reset $end
$var reg 1 ^ DFF $end
$upscope $end
$scope module cir4thbit $end
$var wire 1 _ Din $end
$var wire 1 ` Dout $end
$var wire 1 W Sel $end
$var wire 1 ( clk $end
$var wire 1 ) reset $end
$var reg 1 ` DFF $end
$upscope $end
$upscope $end
$upscope $end
$upscope $end
$enddefinitions $end
$comment Show the parameter values. $end
$dumpall
$end
#0
$dumpvars
0`
0_
0^
0]
0\
0[
0Z
0Y
b0 X
0W
b0 V
0U
0T
0S
0R
0Q
0P
0O
0N
b0 M
0L
b0 K
0J
0I
0H
0G
0F
0E
0D
0C
b0 B
0A
b0 @
0?
0>
0=
0<
0;
0:
09
08
b0 7
06
b0 5
b0 4
b0 3
b0 2
b0 1
b0 0
b0 /
b0 .
b0 -
b0 ,
b0 +
b0 *
1)
0(
b0 '
b0 &
0%
b0 $
b0 #
b0 "
b0 !
$end
#5
1(
#10
0(
0)
#15
1(
#20
16
18
1<
1>
1C
1G
1I
1N
1R
1T
1Y
1]
1_
b1 4
0(
b1101 '
b1101 -
b1101 5
b1101 @
b1101 K
b1101 V
1%
#25
b1101 "
b1101 2
b1101 !
b1101 3
1?
1=
b1101 1
b1101 7
19
1(
#30
06
1A
b0 !
b0 3
b0 "
b0 2
1:
0<
0>
1E
0G
0I
1P
0R
0T
1[
0]
0_
b10 4
0(
b1 $
b1 +
b1 #
b1 *
b11 '
b11 -
b11 5
b11 @
b11 K
b11 V
b1 &
b1 ,
#35
b11 "
b11 2
b11 !
b11 3
1D
b11 0
b11 B
1F
1(
#40
0A
1L
b0 !
b0 3
b0 "
b0 2
08
1>
0C
1I
0N
1T
0Y
1_
b100 4
0(
b10 $
b10 +
b10 #
b10 *
b1010 '
b1010 -
b1010 5
b1010 @
b1010 K
b1010 V
b10 &
b10 ,
#45
b1010 "
b1010 2
b1010 !
b1010 3
1U
b1010 /
b1010 M
1Q
1(
#50
0L
1W
b0 !
b0 3
b0 "
b0 2
18
1<
0>
1C
1G
0I
1N
1R
0T
1Y
1]
0_
b1000 4
0(
b11 $
b11 +
b11 #
b11 *
b111 '
b111 -
b111 5
b111 @
b111 K
b111 V
b11 &
b11 ,
#55
b111 "
b111 2
b111 !
b111 3
1Z
1\
b111 .
b111 X
1^
1(
#60
0W
b1101 !
b1101 3
b1101 "
b1101 2
1>
1I
1T
1_
b0 4
0(
b0 $
b0 +
b0 #
b0 *
b1111 '
b1111 -
b1111 5
b1111 @
b1111 K
b1111 V
b0 &
b0 ,
0%
